{
  "id": 15058890,
  "docket_entries": [
    {
      "id": 64806816,
      "recap_documents": [
        {
          "id": 68940717,
          "absolute_url": "/docket/15058890/1/antonio-r-dasilva-and-isabel-m-dasilva/",
          "date_created": "2019-05-06T18:09:51.342000Z",
          "date_modified": "2019-05-06T18:09:51.345346Z",
          "sha1": "",
          "page_count": null,
          "file_size": null,
          "filepath_local": null,
          "filepath_ia": "",
          "ia_upload_failure_count": null,
          "thumbnail": null,
          "thumbnail_status": 0,
          "ocr_status": null,
          "date_upload": null,
          "document_number": "1",
          "attachment_number": null,
          "pacer_doc_id": "126019852291",
          "is_available": false,
          "is_free_on_pacer": null,
          "is_sealed": null,
          "document_type": 1,
          "description": "Voluntary Petition (Chapter 7)"
        }
      ],
      "date_created": "2019-05-06T18:09:51.335307Z",
      "date_modified": "2019-05-06T18:09:51.336494Z",
      "date_filed": "2019-05-06",
      "entry_number": 1,
      "recap_sequence_number": "2019-05-06.001",
      "pacer_sequence_number": 2,
      "description": ""
    },
    {
      "id": 64806815,
      "recap_documents": [
        {
          "id": 68940716,
          "absolute_url": "/docket/15058890/2/antonio-r-dasilva-and-isabel-m-dasilva/",
          "date_created": "2019-05-06T18:09:51.314203Z",
          "date_modified": "2019-05-06T18:09:51.317730Z",
          "sha1": "",
          "page_count": null,
          "file_size": null,
          "filepath_local": null,
          "filepath_ia": "",
          "ia_upload_failure_count": null,
          "thumbnail": null,
          "thumbnail_status": 0,
          "ocr_status": null,
          "date_upload": null,
          "document_number": "2",
          "attachment_number": null,
          "pacer_doc_id": "126019852296",
          "is_available": false,
          "is_free_on_pacer": null,
          "is_sealed": null,
          "document_type": 1,
          "description": "Chapter 7 Statements of Monthly Income (122A-1) / Exemption Presumption of Abuse (122A-1Supp)"
        }
      ],
      "date_created": "2019-05-06T18:09:51.306248Z",
      "date_modified": "2019-05-06T18:09:51.308093Z",
      "date_filed": "2019-05-06",
      "entry_number": 2,
      "recap_sequence_number": "2019-05-06.001",
      "pacer_sequence_number": 9,
      "description": ""
    },
    {
      "id": 64806814,
      "recap_documents": [
        {
          "id": 68940715,
          "absolute_url": "/docket/15058890/3/antonio-r-dasilva-and-isabel-m-dasilva/",
          "date_created": "2019-05-06T18:09:51.285555Z",
          "date_modified": "2019-05-06T18:09:51.288868Z",
          "sha1": "",
          "page_count": null,
          "file_size": null,
          "filepath_local": null,
          "filepath_ia": "",
          "ia_upload_failure_count": null,
          "thumbnail": null,
          "thumbnail_status": 0,
          "ocr_status": null,
          "date_upload": null,
          "document_number": "3",
          "attachment_number": null,
          "pacer_doc_id": "126019852299",
          "is_available": false,
          "is_free_on_pacer": null,
          "is_sealed": null,
          "document_type": 1,
          "description": "Certificate of Credit Counseling"
        }
      ],
      "date_created": "2019-05-06T18:09:51.278412Z",
      "date_modified": "2019-05-06T18:09:51.279761Z",
      "date_filed": "2019-05-06",
      "entry_number": 3,
      "recap_sequence_number": "2019-05-06.001",
      "pacer_sequence_number": 11,
      "description": ""
    },
    {
      "id": 64835175,
      "recap_documents": [
        {
          "id": 68969296,
          "absolute_url": "/docket/15058890/4/antonio-r-dasilva-and-isabel-m-dasilva/",
          "date_created": "2019-05-06T20:07:32.569874Z",
          "date_modified": "2019-05-06T20:07:32.573039Z",
          "sha1": "",
          "page_count": null,
          "file_size": null,
          "filepath_local": null,
          "filepath_ia": "",
          "ia_upload_failure_count": null,
          "thumbnail": null,
          "thumbnail_status": 0,
          "ocr_status": null,
          "date_upload": null,
          "document_number": "4",
          "attachment_number": null,
          "pacer_doc_id": "126019853761",
          "is_available": false,
          "is_free_on_pacer": null,
          "is_sealed": null,
          "document_type": 1,
          "description": "341(a) Notice (Chapter 7 Individual) (BNC)"
        }
      ],
      "date_created": "2019-05-06T20:07:32.563476Z",
      "date_modified": "2019-05-06T20:07:32.564702Z",
      "date_filed": "2019-05-06",
      "entry_number": 4,
      "recap_sequence_number": "2019-05-06.001",
      "pacer_sequence_number": 16,
      "description": ""
    },
    {
      "id": 64835164,
      "recap_documents": [
        {
          "id": 68969285,
          "absolute_url": "/docket/15058890/5/antonio-r-dasilva-and-isabel-m-dasilva/",
          "date_created": "2019-05-06T20:07:32.429739Z",
          "date_modified": "2019-05-06T20:07:32.433838Z",
          "sha1": "",
          "page_count": null,
          "file_size": null,
          "filepath_local": null,
          "filepath_ia": "",
          "ia_upload_failure_count": null,
          "thumbnail": null,
          "thumbnail_status": 0,
          "ocr_status": null,
          "date_upload": null,
          "document_number": "5",
          "attachment_number": null,
          "pacer_doc_id": "126019853788",
          "is_available": false,
          "is_free_on_pacer": null,
          "is_sealed": null,
          "document_type": 1,
          "description": "341(a) Notice (Chapter 7 Individual) (BNC)"
        }
      ],
      "date_created": "2019-05-06T20:07:32.422982Z",
      "date_modified": "2019-05-06T20:07:32.424354Z",
      "date_filed": "2019-05-06",
      "entry_number": 5,
      "recap_sequence_number": "2019-05-06.001",
      "pacer_sequence_number": 19,
      "description": ""
    },
    {
      "id": 64806812,
      "recap_documents": [
        {
          "id": 68940713,
          "absolute_url": "/docket/15058890//antonio-r-dasilva-and-isabel-m-dasilva/",
          "date_created": "2019-05-06T18:09:51.228839Z",
          "date_modified": "2019-05-06T18:09:51.232532Z",
          "sha1": "",
          "page_count": null,
          "file_size": null,
          "filepath_local": null,
          "filepath_ia": "",
          "ia_upload_failure_count": null,
          "thumbnail": null,
          "thumbnail_status": 0,
          "ocr_status": null,
          "date_upload": null,
          "document_number": "",
          "attachment_number": null,
          "pacer_doc_id": "",
          "is_available": false,
          "is_free_on_pacer": null,
          "is_sealed": null,
          "document_type": 1,
          "description": "Auto - docket of credit card"
        }
      ],
      "date_created": "2019-05-06T18:09:51.222799Z",
      "date_modified": "2019-05-06T18:09:51.222823Z",
      "date_filed": "2019-05-06",
      "entry_number": null,
      "recap_sequence_number": "2019-05-06.001",
      "pacer_sequence_number": null,
      "description": ""
    },
    {
      "id": 65183554,
      "recap_documents": [
        {
          "id": 69320385,
          "absolute_url": "/docket/15058890/6/antonio-r-dasilva-and-isabel-m-dasilva/",
          "date_created": "2019-05-09T05:10:30.477784Z",
          "date_modified": "2019-05-09T05:10:30.481925Z",
          "sha1": "",
          "page_count": null,
          "file_size": null,
          "filepath_local": null,
          "filepath_ia": "",
          "ia_upload_failure_count": null,
          "thumbnail": null,
          "thumbnail_status": 0,
          "ocr_status": null,
          "date_upload": null,
          "document_number": "6",
          "attachment_number": null,
          "pacer_doc_id": "126019862301",
          "is_available": false,
          "is_free_on_pacer": null,
          "is_sealed": null,
          "document_type": 1,
          "description": "Certificate of Mailing - 341(a) Meeting"
        }
      ],
      "date_created": "2019-05-09T05:10:30.471521Z",
      "date_modified": "2019-05-09T05:10:30.472421Z",
      "date_filed": "2019-05-09",
      "entry_number": 6,
      "recap_sequence_number": "2019-05-09.001",
      "pacer_sequence_number": 21,
      "description": ""
    },
    {
      "id": 65183548,
      "recap_documents": [
        {
          "id": 69320379,
          "absolute_url": "/docket/15058890/7/antonio-r-dasilva-and-isabel-m-dasilva/",
          "date_created": "2019-05-09T05:10:30.447494Z",
          "date_modified": "2019-05-09T05:10:30.451041Z",
          "sha1": "",
          "page_count": null,
          "file_size": null,
          "filepath_local": null,
          "filepath_ia": "",
          "ia_upload_failure_count": null,
          "thumbnail": null,
          "thumbnail_status": 0,
          "ocr_status": null,
          "date_upload": null,
          "document_number": "7",
          "attachment_number": null,
          "pacer_doc_id": "126019862302",
          "is_available": false,
          "is_free_on_pacer": null,
          "is_sealed": null,
          "document_type": 1,
          "description": "Certificate of Mailing - 341(a) Meeting"
        }
      ],
      "date_created": "2019-05-09T05:10:30.438089Z",
      "date_modified": "2019-05-09T05:10:30.439429Z",
      "date_filed": "2019-05-09",
      "entry_number": 7,
      "recap_sequence_number": "2019-05-09.001",
      "pacer_sequence_number": 23,
      "description": ""
    },
    {
      "id": 85449895,
      "recap_documents": [
        {
          "id": 89611438,
          "absolute_url": "/docket/15058890/8/antonio-r-dasilva-and-isabel-m-dasilva/",
          "date_created": "2019-06-03T18:08:56.295266Z",
          "date_modified": "2019-06-03T18:08:56.299844Z",
          "sha1": "",
          "page_count": null,
          "file_size": null,
          "filepath_local": null,
          "filepath_ia": "",
          "ia_upload_failure_count": null,
          "thumbnail": null,
          "thumbnail_status": 0,
          "ocr_status": null,
          "date_upload": null,
          "document_number": "8",
          "attachment_number": null,
          "pacer_doc_id": "126019937385",
          "is_available": false,
          "is_free_on_pacer": null,
          "is_sealed": null,
          "document_type": 1,
          "description": "Disclosure of Compensation of Attorney For Debtor (Rule 2016(b)) - Form 2030"
        }
      ],
      "date_created": "2019-06-03T18:08:56.284413Z",
      "date_modified": "2019-06-03T18:08:56.285669Z",
      "date_filed": "2019-06-03",
      "entry_number": 8,
      "recap_sequence_number": "2019-06-03.001",
      "pacer_sequence_number": 25,
      "description": ""
    },
    {
      "id": 87026286,
      "recap_documents": [
        {
          "id": 91201015,
          "absolute_url": "/docket/15058890//antonio-r-dasilva-and-isabel-m-dasilva/",
          "date_created": "2019-06-17T16:38:24.444741Z",
          "date_modified": "2019-06-17T16:38:24.447011Z",
          "sha1": "",
          "page_count": null,
          "file_size": null,
          "filepath_local": null,
          "filepath_ia": "",
          "ia_upload_failure_count": null,
          "thumbnail": null,
          "thumbnail_status": 0,
          "ocr_status": null,
          "date_upload": null,
          "document_number": "",
          "attachment_number": null,
          "pacer_doc_id": "",
          "is_available": false,
          "is_free_on_pacer": null,
          "is_sealed": null,
          "document_type": 1,
          "description": "Chapter 7 Trustee's Report of No Distribution"
        }
      ],
      "date_created": "2019-06-17T16:38:24.440846Z",
      "date_modified": "2019-06-17T16:38:24.440863Z",
      "date_filed": "2019-06-17",
      "entry_number": null,
      "recap_sequence_number": "2019-06-17.001",
      "pacer_sequence_number": null,
      "description": ""
    },
    {
      "id": 96948823,
      "recap_documents": [
        {
          "id": 101169928,
          "absolute_url": "/docket/15058890/10/antonio-r-dasilva-and-isabel-m-dasilva/",
          "date_created": "2019-07-31T21:10:51.999975Z",
          "date_modified": "2019-07-31T21:10:52.003923Z",
          "sha1": "",
          "page_count": null,
          "file_size": null,
          "filepath_local": null,
          "filepath_ia": "",
          "ia_upload_failure_count": null,
          "thumbnail": null,
          "thumbnail_status": 0,
          "ocr_status": null,
          "date_upload": null,
          "document_number": "10",
          "attachment_number": null,
          "pacer_doc_id": "126020099213",
          "is_available": false,
          "is_free_on_pacer": null,
          "is_sealed": null,
          "document_type": 1,
          "description": "Notice, Appearance"
        }
      ],
      "date_created": "2019-07-31T21:10:51.990945Z",
      "date_modified": "2019-07-31T21:10:51.992174Z",
      "date_filed": "2019-07-31",
      "entry_number": 10,
      "recap_sequence_number": "2019-07-31.001",
      "pacer_sequence_number": 29,
      "description": ""
    },
    {
      "id": 97229662,
      "recap_documents": [
        {
          "id": 101453036,
          "absolute_url": "/docket/15058890/11/antonio-r-dasilva-and-isabel-m-dasilva/",
          "date_created": "2019-08-02T17:21:32.187618Z",
          "date_modified": "2019-08-02T17:21:32.191356Z",
          "sha1": "",
          "page_count": null,
          "file_size": null,
          "filepath_local": null,
          "filepath_ia": "",
          "ia_upload_failure_count": null,
          "thumbnail": null,
          "thumbnail_status": 0,
          "ocr_status": null,
          "date_upload": null,
          "document_number": "11",
          "attachment_number": null,
          "pacer_doc_id": "126020105108",
          "is_available": false,
          "is_free_on_pacer": null,
          "is_sealed": null,
          "document_type": 1,
          "description": "Motion, Stay"
        }
      ],
      "date_created": "2019-08-02T17:21:32.181581Z",
      "date_modified": "2019-08-02T17:21:32.182462Z",
      "date_filed": "2019-08-02",
      "entry_number": 11,
      "recap_sequence_number": "2019-08-02.001",
      "pacer_sequence_number": 33,
      "description": ""
    },
    {
      "id": 97229642,
      "recap_documents": [
        {
          "id": 101453016,
          "absolute_url": "/docket/15058890/12/antonio-r-dasilva-and-isabel-m-dasilva/",
          "date_created": "2019-08-02T17:21:31.888440Z",
          "date_modified": "2019-08-02T17:21:31.892919Z",
          "sha1": "",
          "page_count": null,
          "file_size": null,
          "filepath_local": null,
          "filepath_ia": "",
          "ia_upload_failure_count": null,
          "thumbnail": null,
          "thumbnail_status": 0,
          "ocr_status": null,
          "date_upload": null,
          "document_number": "12",
          "attachment_number": null,
          "pacer_doc_id": "126020105158",
          "is_available": false,
          "is_free_on_pacer": null,
          "is_sealed": null,
          "document_type": 1,
          "description": "Motion, Relief from Stay (fee)"
        }
      ],
      "date_created": "2019-08-02T17:21:31.881461Z",
      "date_modified": "2019-08-02T17:21:31.882449Z",
      "date_filed": "2019-08-02",
      "entry_number": 12,
      "recap_sequence_number": "2019-08-02.001",
      "pacer_sequence_number": 35,
      "description": ""
    },
    {
      "id": 98413858,
      "recap_documents": [
        {
          "id": 102645844,
          "absolute_url": "/docket/15058890/13/antonio-r-dasilva-and-isabel-m-dasilva/",
          "date_created": "2019-08-13T16:20:43.808920Z",
          "date_modified": "2019-08-13T16:20:43.812023Z",
          "sha1": "",
          "page_count": null,
          "file_size": null,
          "filepath_local": null,
          "filepath_ia": "",
          "ia_upload_failure_count": null,
          "thumbnail": null,
          "thumbnail_status": 0,
          "ocr_status": null,
          "date_upload": null,
          "document_number": "13",
          "attachment_number": null,
          "pacer_doc_id": "126020132647",
          "is_available": false,
          "is_free_on_pacer": null,
          "is_sealed": null,
          "document_type": 1,
          "description": "Notice of Requirement to Complete Course in Financial Management (Chapter 7 & 13)"
        }
      ],
      "date_created": "2019-08-13T16:20:43.802883Z",
      "date_modified": "2019-08-13T16:20:43.803818Z",
      "date_filed": "2019-08-13",
      "entry_number": 13,
      "recap_sequence_number": "2019-08-13.001",
      "pacer_sequence_number": 37,
      "description": ""
    },
    {
      "id": 98814620,
      "recap_documents": [
        {
          "id": 103049440,
          "absolute_url": "/docket/15058890/14/antonio-r-dasilva-and-isabel-m-dasilva/",
          "date_created": "2019-08-16T04:29:35.001021Z",
          "date_modified": "2019-08-16T04:29:35.004827Z",
          "sha1": "",
          "page_count": null,
          "file_size": null,
          "filepath_local": null,
          "filepath_ia": "",
          "ia_upload_failure_count": null,
          "thumbnail": null,
          "thumbnail_status": 0,
          "ocr_status": null,
          "date_upload": null,
          "document_number": "14",
          "attachment_number": null,
          "pacer_doc_id": "126020141394",
          "is_available": false,
          "is_free_on_pacer": null,
          "is_sealed": null,
          "document_type": 1,
          "description": "Certificate of Mailing - Ntc of Request to Complete Course"
        }
      ],
      "date_created": "2019-08-16T04:29:34.992669Z",
      "date_modified": "2019-08-16T04:29:34.993849Z",
      "date_filed": "2019-08-16",
      "entry_number": 14,
      "recap_sequence_number": "2019-08-16.001",
      "pacer_sequence_number": 40,
      "description": ""
    }
  ],
  "parties": [],
  "original_court_info": null,
  "bankruptcy_information": null,
  "claims": [],
  "idb_data": null,
  "absolute_url": "/docket/15058890/antonio-r-dasilva-and-isabel-m-dasilva/",
  "source": 1,
  "appeal_from_str": "",
  "assigned_to_str": "",
  "referred_to_str": "",
  "panel_str": "",
  "date_created": "2019-05-06T18:09:51.218499Z",
  "date_modified": "2019-08-16T04:29:34.985432Z",
  "date_last_index": null,
  "date_cert_granted": null,
  "date_cert_denied": null,
  "date_argued": null,
  "date_reargued": null,
  "date_reargument_denied": null,
  "date_filed": null,
  "date_terminated": null,
  "date_last_filing": null,
  "case_name_short": "",
  "case_name": "Antonio R. DaSilva and Isabel M. DaSilva",
  "case_name_full": "",
  "slug": "antonio-r-dasilva-and-isabel-m-dasilva",
  "docket_number": "19-22934",
  "docket_number_core": "",
  "pacer_case_id": "292800",
  "cause": "",
  "nature_of_suit": "",
  "jury_demand": "",
  "jurisdiction_type": "",
  "appellate_fee_status": "",
  "appellate_case_type_information": "",
  "mdl_status": "",
  "filepath_local": null,
  "filepath_ia": "",
  "filepath_ia_json": "",
  "date_blocked": "2019-05-06",
  "blocked": true,
  "court": "nysb",
  "appeal_from": null,
  "assigned_to": null,
  "referred_to": null,
  "panel": []
}