{
  "id": 7067303,
  "docket_entries": [
    {
      "id": 28056890,
      "recap_documents": [
        {
          "id": 30141550,
          "absolute_url": "/docket/7067303/1/joseph-p-perniciaro/",
          "date_created": "2018-06-06T18:21:18.594693Z",
          "date_modified": "2018-06-06T18:21:18.596642Z",
          "sha1": "",
          "page_count": null,
          "file_size": null,
          "filepath_local": null,
          "filepath_ia": "",
          "ia_upload_failure_count": null,
          "thumbnail": null,
          "thumbnail_status": 0,
          "ocr_status": null,
          "date_upload": null,
          "document_number": "1",
          "attachment_number": null,
          "pacer_doc_id": "126018958209",
          "is_available": false,
          "is_free_on_pacer": null,
          "is_sealed": null,
          "document_type": 1,
          "description": "Voluntary Petition (Chapter 7)"
        }
      ],
      "date_created": "2018-06-06T18:21:18.590702Z",
      "date_modified": "2018-06-06T18:21:18.591251Z",
      "date_filed": "2018-06-06",
      "entry_number": 1,
      "recap_sequence_number": "2018-06-06.001",
      "pacer_sequence_number": null,
      "description": ""
    },
    {
      "id": 28056889,
      "recap_documents": [
        {
          "id": 30141549,
          "absolute_url": "/docket/7067303/2/joseph-p-perniciaro/",
          "date_created": "2018-06-06T18:21:18.573819Z",
          "date_modified": "2018-06-06T18:21:18.575701Z",
          "sha1": "",
          "page_count": null,
          "file_size": null,
          "filepath_local": null,
          "filepath_ia": "",
          "ia_upload_failure_count": null,
          "thumbnail": null,
          "thumbnail_status": 0,
          "ocr_status": null,
          "date_upload": null,
          "document_number": "2",
          "attachment_number": null,
          "pacer_doc_id": "126018958212",
          "is_available": false,
          "is_free_on_pacer": null,
          "is_sealed": null,
          "document_type": 1,
          "description": "Chapter 7 Statements of Monthly Income (122A-1) / Exemption Presumption of Abuse (122A-1Supp)"
        }
      ],
      "date_created": "2018-06-06T18:21:18.569733Z",
      "date_modified": "2018-06-06T18:21:18.570345Z",
      "date_filed": "2018-06-06",
      "entry_number": 2,
      "recap_sequence_number": "2018-06-06.001",
      "pacer_sequence_number": null,
      "description": ""
    },
    {
      "id": 28056888,
      "recap_documents": [
        {
          "id": 30141548,
          "absolute_url": "/docket/7067303/3/joseph-p-perniciaro/",
          "date_created": "2018-06-06T18:21:18.552669Z",
          "date_modified": "2018-06-06T18:21:18.554704Z",
          "sha1": "",
          "page_count": null,
          "file_size": null,
          "filepath_local": null,
          "filepath_ia": "",
          "ia_upload_failure_count": null,
          "thumbnail": null,
          "thumbnail_status": 0,
          "ocr_status": null,
          "date_upload": null,
          "document_number": "3",
          "attachment_number": null,
          "pacer_doc_id": "126018958215",
          "is_available": false,
          "is_free_on_pacer": null,
          "is_sealed": null,
          "document_type": 1,
          "description": "Certificate of Credit Counseling"
        }
      ],
      "date_created": "2018-06-06T18:21:18.548686Z",
      "date_modified": "2018-06-06T18:21:18.549241Z",
      "date_filed": "2018-06-06",
      "entry_number": 3,
      "recap_sequence_number": "2018-06-06.001",
      "pacer_sequence_number": null,
      "description": ""
    },
    {
      "id": 28056857,
      "recap_documents": [
        {
          "id": 30141517,
          "absolute_url": "/docket/7067303/4/joseph-p-perniciaro/",
          "date_created": "2018-06-06T18:21:16.573975Z",
          "date_modified": "2018-06-06T18:21:16.575940Z",
          "sha1": "",
          "page_count": null,
          "file_size": null,
          "filepath_local": null,
          "filepath_ia": "",
          "ia_upload_failure_count": null,
          "thumbnail": null,
          "thumbnail_status": 0,
          "ocr_status": null,
          "date_upload": null,
          "document_number": "4",
          "attachment_number": null,
          "pacer_doc_id": "126018958377",
          "is_available": false,
          "is_free_on_pacer": null,
          "is_sealed": null,
          "document_type": 1,
          "description": "Disclosure of Compensation of Attorney For Debtor (Rule 2016(b)) - Form 2030"
        }
      ],
      "date_created": "2018-06-06T18:21:16.569990Z",
      "date_modified": "2018-06-06T18:21:16.570530Z",
      "date_filed": "2018-06-06",
      "entry_number": 4,
      "recap_sequence_number": "2018-06-06.001",
      "pacer_sequence_number": null,
      "description": ""
    },
    {
      "id": 28157578,
      "recap_documents": [
        {
          "id": 30242927,
          "absolute_url": "/docket/7067303/5/joseph-p-perniciaro/",
          "date_created": "2018-06-07T15:24:22.455019Z",
          "date_modified": "2018-06-07T15:24:22.457349Z",
          "sha1": "",
          "page_count": null,
          "file_size": null,
          "filepath_local": null,
          "filepath_ia": "",
          "ia_upload_failure_count": null,
          "thumbnail": null,
          "thumbnail_status": 0,
          "ocr_status": null,
          "date_upload": null,
          "document_number": "5",
          "attachment_number": null,
          "pacer_doc_id": "126018961045",
          "is_available": false,
          "is_free_on_pacer": null,
          "is_sealed": null,
          "document_type": 1,
          "description": "341(a) Notice (Chapter 7 Individual) (BNC)"
        }
      ],
      "date_created": "2018-06-07T15:24:22.449500Z",
      "date_modified": "2018-06-07T15:24:22.450293Z",
      "date_filed": "2018-06-07",
      "entry_number": 5,
      "recap_sequence_number": "2018-06-07.001",
      "pacer_sequence_number": null,
      "description": ""
    },
    {
      "id": 28405074,
      "recap_documents": [
        {
          "id": 30491916,
          "absolute_url": "/docket/7067303/6/joseph-p-perniciaro/",
          "date_created": "2018-06-10T05:18:47.066042Z",
          "date_modified": "2018-06-10T05:18:47.068046Z",
          "sha1": "",
          "page_count": null,
          "file_size": null,
          "filepath_local": null,
          "filepath_ia": "",
          "ia_upload_failure_count": null,
          "thumbnail": null,
          "thumbnail_status": 0,
          "ocr_status": null,
          "date_upload": null,
          "document_number": "6",
          "attachment_number": null,
          "pacer_doc_id": "126018967935",
          "is_available": false,
          "is_free_on_pacer": null,
          "is_sealed": null,
          "document_type": 1,
          "description": "Certificate of Mailing - 341(a) Meeting"
        }
      ],
      "date_created": "2018-06-10T05:18:47.061672Z",
      "date_modified": "2018-06-10T05:18:47.062288Z",
      "date_filed": "2018-06-10",
      "entry_number": 6,
      "recap_sequence_number": "2018-06-10.001",
      "pacer_sequence_number": null,
      "description": ""
    },
    {
      "id": 29908970,
      "recap_documents": [
        {
          "id": 32006631,
          "absolute_url": "/docket/7067303/7/joseph-p-perniciaro/",
          "date_created": "2018-06-26T07:14:07.838675Z",
          "date_modified": "2018-06-26T07:14:07.841625Z",
          "sha1": "",
          "page_count": null,
          "file_size": null,
          "filepath_local": null,
          "filepath_ia": "",
          "ia_upload_failure_count": null,
          "thumbnail": null,
          "thumbnail_status": 0,
          "ocr_status": null,
          "date_upload": null,
          "document_number": "7",
          "attachment_number": null,
          "pacer_doc_id": "126019011430",
          "is_available": false,
          "is_free_on_pacer": null,
          "is_sealed": null,
          "document_type": 1,
          "description": "Personal Financial Management Course Certificate Filed By Provider"
        }
      ],
      "date_created": "2018-06-26T07:14:07.819124Z",
      "date_modified": "2018-06-26T07:14:07.831482Z",
      "date_filed": "2018-06-26",
      "entry_number": 7,
      "recap_sequence_number": "2018-06-26.001",
      "pacer_sequence_number": null,
      "description": ""
    }
  ],
  "parties": [],
  "original_court_info": null,
  "bankruptcy_information": null,
  "claims": [],
  "idb_data": null,
  "absolute_url": "/docket/7067303/joseph-p-perniciaro/",
  "source": 1,
  "appeal_from_str": "",
  "assigned_to_str": "",
  "referred_to_str": "",
  "panel_str": "",
  "date_created": "2018-06-06T18:21:16.567819Z",
  "date_modified": "2018-11-09T18:56:46.670571Z",
  "date_last_index": "2018-11-09T18:56:46.670122Z",
  "date_cert_granted": null,
  "date_cert_denied": null,
  "date_argued": null,
  "date_reargued": null,
  "date_reargument_denied": null,
  "date_filed": null,
  "date_terminated": null,
  "date_last_filing": null,
  "case_name_short": "Joseph P Perniciaro",
  "case_name": "Joseph P Perniciaro",
  "case_name_full": "",
  "slug": "joseph-p-perniciaro",
  "docket_number": "18-11741",
  "docket_number_core": "",
  "pacer_case_id": "284197",
  "cause": "",
  "nature_of_suit": "",
  "jury_demand": "",
  "jurisdiction_type": "",
  "appellate_fee_status": "",
  "appellate_case_type_information": "",
  "mdl_status": "",
  "filepath_local": null,
  "filepath_ia": "",
  "filepath_ia_json": "https://archive.org/download/gov.uscourts.nysb.284197/gov.uscourts.nysb.284197.docket.json",
  "date_blocked": "2018-06-08",
  "blocked": true,
  "court": "nysb",
  "appeal_from": null,
  "assigned_to": null,
  "referred_to": null,
  "panel": []
}