{
  "id": 7635495,
  "docket_entries": [
    {
      "id": 34579741,
      "recap_documents": [
        {
          "id": 36759077,
          "absolute_url": "/docket/7635495/1/charles-marvin-graham-iv/",
          "date_created": "2018-08-10T04:23:25.782524Z",
          "date_modified": "2018-08-10T04:23:25.785027Z",
          "sha1": "",
          "page_count": null,
          "file_size": null,
          "filepath_local": null,
          "filepath_ia": "",
          "ia_upload_failure_count": null,
          "thumbnail": null,
          "thumbnail_status": 0,
          "ocr_status": null,
          "date_upload": null,
          "document_number": "1",
          "attachment_number": null,
          "pacer_doc_id": "14604731869",
          "is_available": false,
          "is_free_on_pacer": null,
          "is_sealed": null,
          "document_type": 1,
          "description": "Voluntary Petition (Chapter 13)"
        }
      ],
      "date_created": "2018-08-10T04:23:25.777096Z",
      "date_modified": "2018-08-10T04:23:25.778086Z",
      "date_filed": "2018-08-10",
      "entry_number": 1,
      "recap_sequence_number": "2018-08-10.001",
      "pacer_sequence_number": null,
      "description": ""
    },
    {
      "id": 34579739,
      "recap_documents": [
        {
          "id": 36759075,
          "absolute_url": "/docket/7635495/3/charles-marvin-graham-iv/",
          "date_created": "2018-08-10T04:23:25.729700Z",
          "date_modified": "2018-08-10T04:23:25.756825Z",
          "sha1": "",
          "page_count": null,
          "file_size": null,
          "filepath_local": null,
          "filepath_ia": "",
          "ia_upload_failure_count": null,
          "thumbnail": null,
          "thumbnail_status": 0,
          "ocr_status": null,
          "date_upload": null,
          "document_number": "3",
          "attachment_number": null,
          "pacer_doc_id": "14604731875",
          "is_available": false,
          "is_free_on_pacer": null,
          "is_sealed": null,
          "document_type": 1,
          "description": "Chapter 13 Calculation of Disposable Income - Form 122C-2"
        }
      ],
      "date_created": "2018-08-10T04:23:25.724436Z",
      "date_modified": "2018-08-10T04:23:25.751370Z",
      "date_filed": "2018-08-10",
      "entry_number": 3,
      "recap_sequence_number": "2018-08-10.001",
      "pacer_sequence_number": null,
      "description": ""
    },
    {
      "id": 34579738,
      "recap_documents": [
        {
          "id": 36759074,
          "absolute_url": "/docket/7635495/4/charles-marvin-graham-iv/",
          "date_created": "2018-08-10T04:23:25.697061Z",
          "date_modified": "2018-08-10T04:23:25.699854Z",
          "sha1": "",
          "page_count": null,
          "file_size": null,
          "filepath_local": null,
          "filepath_ia": "",
          "ia_upload_failure_count": null,
          "thumbnail": null,
          "thumbnail_status": 0,
          "ocr_status": null,
          "date_upload": null,
          "document_number": "4",
          "attachment_number": null,
          "pacer_doc_id": "14604731878",
          "is_available": false,
          "is_free_on_pacer": null,
          "is_sealed": null,
          "document_type": 1,
          "description": "Certificate of Credit Counseling"
        }
      ],
      "date_created": "2018-08-10T04:23:25.691248Z",
      "date_modified": "2018-08-10T04:23:25.692335Z",
      "date_filed": "2018-08-10",
      "entry_number": 4,
      "recap_sequence_number": "2018-08-10.001",
      "pacer_sequence_number": null,
      "description": ""
    },
    {
      "id": 34579737,
      "recap_documents": [
        {
          "id": 36759073,
          "absolute_url": "/docket/7635495/5/charles-marvin-graham-iv/",
          "date_created": "2018-08-10T04:23:25.666835Z",
          "date_modified": "2018-08-10T04:23:25.670635Z",
          "sha1": "",
          "page_count": null,
          "file_size": null,
          "filepath_local": null,
          "filepath_ia": "",
          "ia_upload_failure_count": null,
          "thumbnail": null,
          "thumbnail_status": 0,
          "ocr_status": null,
          "date_upload": null,
          "document_number": "5",
          "attachment_number": null,
          "pacer_doc_id": "14604731881",
          "is_available": false,
          "is_free_on_pacer": null,
          "is_sealed": null,
          "document_type": 1,
          "description": "Payment Advices Certification"
        }
      ],
      "date_created": "2018-08-10T04:23:25.659415Z",
      "date_modified": "2018-08-10T04:23:25.661005Z",
      "date_filed": "2018-08-10",
      "entry_number": 5,
      "recap_sequence_number": "2018-08-10.001",
      "pacer_sequence_number": null,
      "description": ""
    },
    {
      "id": 34626551,
      "recap_documents": [
        {
          "id": 36806331,
          "absolute_url": "/docket/7635495/7/charles-marvin-graham-iv/",
          "date_created": "2018-08-10T15:23:30.208296Z",
          "date_modified": "2018-08-10T15:23:30.215614Z",
          "sha1": "",
          "page_count": null,
          "file_size": null,
          "filepath_local": null,
          "filepath_ia": "",
          "ia_upload_failure_count": null,
          "thumbnail": null,
          "thumbnail_status": 0,
          "ocr_status": null,
          "date_upload": null,
          "document_number": "7",
          "attachment_number": null,
          "pacer_doc_id": "14604732083",
          "is_available": false,
          "is_free_on_pacer": null,
          "is_sealed": null,
          "document_type": 1,
          "description": "Meeting of Creditors 13"
        }
      ],
      "date_created": "2018-08-10T15:23:30.194138Z",
      "date_modified": "2018-08-10T15:23:30.195472Z",
      "date_filed": "2018-08-10",
      "entry_number": 7,
      "recap_sequence_number": "2018-08-10.001",
      "pacer_sequence_number": null,
      "description": ""
    },
    {
      "id": 34758251,
      "recap_documents": [
        {
          "id": 36938948,
          "absolute_url": "/docket/7635495/8/charles-marvin-graham-iv/",
          "date_created": "2018-08-13T04:33:03.811024Z",
          "date_modified": "2018-08-13T04:33:03.813896Z",
          "sha1": "",
          "page_count": null,
          "file_size": null,
          "filepath_local": null,
          "filepath_ia": "",
          "ia_upload_failure_count": null,
          "thumbnail": null,
          "thumbnail_status": 0,
          "ocr_status": null,
          "date_upload": null,
          "document_number": "8",
          "attachment_number": null,
          "pacer_doc_id": "14604732790",
          "is_available": false,
          "is_free_on_pacer": null,
          "is_sealed": null,
          "document_type": 1,
          "description": "BNC Certificate of Mailing - Meeting of Creditors"
        }
      ],
      "date_created": "2018-08-13T04:33:03.769399Z",
      "date_modified": "2018-08-13T04:33:03.770141Z",
      "date_filed": "2018-08-13",
      "entry_number": 8,
      "recap_sequence_number": "2018-08-13.001",
      "pacer_sequence_number": null,
      "description": ""
    },
    {
      "id": 34758248,
      "recap_documents": [
        {
          "id": 36938945,
          "absolute_url": "/docket/7635495/9/charles-marvin-graham-iv/",
          "date_created": "2018-08-13T04:33:03.665954Z",
          "date_modified": "2018-08-13T04:33:03.669197Z",
          "sha1": "",
          "page_count": null,
          "file_size": null,
          "filepath_local": null,
          "filepath_ia": "",
          "ia_upload_failure_count": null,
          "thumbnail": null,
          "thumbnail_status": 0,
          "ocr_status": null,
          "date_upload": null,
          "document_number": "9",
          "attachment_number": null,
          "pacer_doc_id": "14604732791",
          "is_available": false,
          "is_free_on_pacer": null,
          "is_sealed": null,
          "document_type": 1,
          "description": "BNC Certificate of Mailing - PDF Document"
        }
      ],
      "date_created": "2018-08-13T04:33:03.606186Z",
      "date_modified": "2018-08-13T04:33:03.607466Z",
      "date_filed": "2018-08-13",
      "entry_number": 9,
      "recap_sequence_number": "2018-08-13.001",
      "pacer_sequence_number": null,
      "description": ""
    },
    {
      "id": 35227652,
      "recap_documents": [
        {
          "id": 37413581,
          "absolute_url": "/docket/7635495/10/charles-marvin-graham-iv/",
          "date_created": "2018-08-16T22:22:52.914970Z",
          "date_modified": "2018-08-16T22:22:52.918243Z",
          "sha1": "",
          "page_count": null,
          "file_size": null,
          "filepath_local": null,
          "filepath_ia": "",
          "ia_upload_failure_count": null,
          "thumbnail": null,
          "thumbnail_status": 0,
          "ocr_status": null,
          "date_upload": null,
          "document_number": "10",
          "attachment_number": null,
          "pacer_doc_id": "14604735280",
          "is_available": false,
          "is_free_on_pacer": null,
          "is_sealed": null,
          "document_type": 1,
          "description": "Wage Deduction Order"
        }
      ],
      "date_created": "2018-08-16T22:22:52.907978Z",
      "date_modified": "2018-08-16T22:22:52.909465Z",
      "date_filed": "2018-08-16",
      "entry_number": 10,
      "recap_sequence_number": "2018-08-16.001",
      "pacer_sequence_number": null,
      "description": ""
    },
    {
      "id": 35405730,
      "recap_documents": [
        {
          "id": 37592854,
          "absolute_url": "/docket/7635495/11/charles-marvin-graham-iv/",
          "date_created": "2018-08-19T13:37:28.213242Z",
          "date_modified": "2018-08-19T13:37:28.216973Z",
          "sha1": "",
          "page_count": null,
          "file_size": null,
          "filepath_local": null,
          "filepath_ia": "",
          "ia_upload_failure_count": null,
          "thumbnail": null,
          "thumbnail_status": 0,
          "ocr_status": null,
          "date_upload": null,
          "document_number": "11",
          "attachment_number": null,
          "pacer_doc_id": "14604736441",
          "is_available": false,
          "is_free_on_pacer": null,
          "is_sealed": null,
          "document_type": 1,
          "description": "Creditor Request for Notices"
        }
      ],
      "date_created": "2018-08-19T13:37:28.203165Z",
      "date_modified": "2018-08-19T13:37:28.206034Z",
      "date_filed": "2018-08-19",
      "entry_number": 11,
      "recap_sequence_number": "2018-08-19.001",
      "pacer_sequence_number": null,
      "description": ""
    },
    {
      "id": 35524599,
      "recap_documents": [
        {
          "id": 37712677,
          "absolute_url": "/docket/7635495/12/charles-marvin-graham-iv/",
          "date_created": "2018-08-20T22:19:39.560976Z",
          "date_modified": "2018-08-20T22:19:39.563755Z",
          "sha1": "",
          "page_count": null,
          "file_size": null,
          "filepath_local": null,
          "filepath_ia": "",
          "ia_upload_failure_count": null,
          "thumbnail": null,
          "thumbnail_status": 0,
          "ocr_status": null,
          "date_upload": null,
          "document_number": "12",
          "attachment_number": null,
          "pacer_doc_id": "14604737047",
          "is_available": false,
          "is_free_on_pacer": null,
          "is_sealed": null,
          "document_type": 1,
          "description": "Certificate of Service"
        }
      ],
      "date_created": "2018-08-20T22:19:39.555862Z",
      "date_modified": "2018-08-20T22:19:39.556754Z",
      "date_filed": "2018-08-20",
      "entry_number": 12,
      "recap_sequence_number": "2018-08-20.001",
      "pacer_sequence_number": null,
      "description": ""
    },
    {
      "id": 36402240,
      "recap_documents": [
        {
          "id": 38599334,
          "absolute_url": "/docket/7635495/14/charles-marvin-graham-iv/",
          "date_created": "2018-08-29T15:35:36.841499Z",
          "date_modified": "2018-08-29T15:35:36.844317Z",
          "sha1": "",
          "page_count": null,
          "file_size": null,
          "filepath_local": null,
          "filepath_ia": "",
          "ia_upload_failure_count": null,
          "thumbnail": null,
          "thumbnail_status": 0,
          "ocr_status": null,
          "date_upload": null,
          "document_number": "14",
          "attachment_number": null,
          "pacer_doc_id": "14604741093",
          "is_available": false,
          "is_free_on_pacer": null,
          "is_sealed": null,
          "document_type": 1,
          "description": "Financial Management Course Certification"
        }
      ],
      "date_created": "2018-08-29T15:35:36.835409Z",
      "date_modified": "2018-08-29T15:35:36.836659Z",
      "date_filed": "2018-08-29",
      "entry_number": 14,
      "recap_sequence_number": "2018-08-29.001",
      "pacer_sequence_number": null,
      "description": ""
    },
    {
      "id": 37045104,
      "recap_documents": [
        {
          "id": 39247967,
          "absolute_url": "/docket/7635495/16/charles-marvin-graham-iv/",
          "date_created": "2018-09-05T23:42:26.362771Z",
          "date_modified": "2018-09-05T23:42:26.365504Z",
          "sha1": "",
          "page_count": null,
          "file_size": null,
          "filepath_local": null,
          "filepath_ia": "",
          "ia_upload_failure_count": null,
          "thumbnail": null,
          "thumbnail_status": 0,
          "ocr_status": null,
          "date_upload": null,
          "document_number": "16",
          "attachment_number": null,
          "pacer_doc_id": "14604745262",
          "is_available": false,
          "is_free_on_pacer": null,
          "is_sealed": null,
          "document_type": 1,
          "description": "Corporate Ownership Statement"
        }
      ],
      "date_created": "2018-09-05T23:42:26.356287Z",
      "date_modified": "2018-09-05T23:42:26.357609Z",
      "date_filed": "2018-09-05",
      "entry_number": 16,
      "recap_sequence_number": "2018-09-05.001",
      "pacer_sequence_number": null,
      "description": ""
    },
    {
      "id": 40347047,
      "recap_documents": [
        {
          "id": 42580208,
          "absolute_url": "/docket/7635495/20/charles-marvin-graham-iv/",
          "date_created": "2018-10-12T20:23:33.564419Z",
          "date_modified": "2018-10-12T20:23:33.568776Z",
          "sha1": "",
          "page_count": null,
          "file_size": null,
          "filepath_local": null,
          "filepath_ia": "",
          "ia_upload_failure_count": null,
          "thumbnail": null,
          "thumbnail_status": 0,
          "ocr_status": null,
          "date_upload": null,
          "document_number": "20",
          "attachment_number": null,
          "pacer_doc_id": "14604764766",
          "is_available": false,
          "is_free_on_pacer": null,
          "is_sealed": null,
          "document_type": 1,
          "description": "Corporate Ownership Statement"
        }
      ],
      "date_created": "2018-10-12T20:23:33.554579Z",
      "date_modified": "2018-10-12T20:23:33.556284Z",
      "date_filed": "2018-10-12",
      "entry_number": 20,
      "recap_sequence_number": "2018-10-12.001",
      "pacer_sequence_number": null,
      "description": ""
    },
    {
      "id": 42194359,
      "recap_documents": [
        {
          "id": 44445299,
          "absolute_url": "/docket/7635495/24/charles-marvin-graham-iv/",
          "date_created": "2018-11-02T15:23:44.315096Z",
          "date_modified": "2018-11-02T15:23:44.318660Z",
          "sha1": "",
          "page_count": null,
          "file_size": null,
          "filepath_local": null,
          "filepath_ia": "",
          "ia_upload_failure_count": null,
          "thumbnail": null,
          "thumbnail_status": 0,
          "ocr_status": null,
          "date_upload": null,
          "document_number": "24",
          "attachment_number": null,
          "pacer_doc_id": "14604775507",
          "is_available": false,
          "is_free_on_pacer": null,
          "is_sealed": null,
          "document_type": 1,
          "description": "Avoid Lien"
        }
      ],
      "date_created": "2018-11-02T15:23:44.307287Z",
      "date_modified": "2018-11-02T15:23:44.308612Z",
      "date_filed": "2018-11-02",
      "entry_number": 24,
      "recap_sequence_number": "2018-11-02.001",
      "pacer_sequence_number": null,
      "description": ""
    },
    {
      "id": 42203188,
      "recap_documents": [
        {
          "id": 44454189,
          "absolute_url": "/docket/7635495/25/charles-marvin-graham-iv/",
          "date_created": "2018-11-02T16:25:50.351689Z",
          "date_modified": "2018-11-02T16:25:50.353911Z",
          "sha1": "",
          "page_count": null,
          "file_size": null,
          "filepath_local": null,
          "filepath_ia": "",
          "ia_upload_failure_count": null,
          "thumbnail": null,
          "thumbnail_status": 0,
          "ocr_status": null,
          "date_upload": null,
          "document_number": "25",
          "attachment_number": null,
          "pacer_doc_id": "14604775523",
          "is_available": false,
          "is_free_on_pacer": null,
          "is_sealed": null,
          "document_type": 1,
          "description": "Avoid Lien"
        }
      ],
      "date_created": "2018-11-02T16:25:50.347058Z",
      "date_modified": "2018-11-02T16:25:50.347766Z",
      "date_filed": "2018-11-02",
      "entry_number": 25,
      "recap_sequence_number": "2018-11-02.001",
      "pacer_sequence_number": null,
      "description": ""
    },
    {
      "id": 42379700,
      "recap_documents": [
        {
          "id": 44632114,
          "absolute_url": "/docket/7635495/32/charles-marvin-graham-iv/",
          "date_created": "2018-11-05T15:18:41.497350Z",
          "date_modified": "2018-11-05T15:18:41.499809Z",
          "sha1": "",
          "page_count": null,
          "file_size": null,
          "filepath_local": null,
          "filepath_ia": "",
          "ia_upload_failure_count": null,
          "thumbnail": null,
          "thumbnail_status": 0,
          "ocr_status": null,
          "date_upload": null,
          "document_number": "32",
          "attachment_number": null,
          "pacer_doc_id": "14604776368",
          "is_available": false,
          "is_free_on_pacer": null,
          "is_sealed": null,
          "document_type": 1,
          "description": "Order Setting Deadline for Objection to Confirmation"
        }
      ],
      "date_created": "2018-11-05T15:18:41.492103Z",
      "date_modified": "2018-11-05T15:18:41.492838Z",
      "date_filed": "2018-11-05",
      "entry_number": 32,
      "recap_sequence_number": "2018-11-05.001",
      "pacer_sequence_number": null,
      "description": ""
    },
    {
      "id": 42379677,
      "recap_documents": [
        {
          "id": 44632092,
          "absolute_url": "/docket/7635495/33/charles-marvin-graham-iv/",
          "date_created": "2018-11-05T15:18:41.313865Z",
          "date_modified": "2018-11-05T15:18:41.317928Z",
          "sha1": "",
          "page_count": null,
          "file_size": null,
          "filepath_local": null,
          "filepath_ia": "",
          "ia_upload_failure_count": null,
          "thumbnail": null,
          "thumbnail_status": 0,
          "ocr_status": null,
          "date_upload": null,
          "document_number": "33",
          "attachment_number": null,
          "pacer_doc_id": "14604776399",
          "is_available": false,
          "is_free_on_pacer": null,
          "is_sealed": null,
          "document_type": 1,
          "description": "Certificate of Service"
        }
      ],
      "date_created": "2018-11-05T15:18:41.305931Z",
      "date_modified": "2018-11-05T15:18:41.306994Z",
      "date_filed": "2018-11-05",
      "entry_number": 33,
      "recap_sequence_number": "2018-11-05.001",
      "pacer_sequence_number": null,
      "description": ""
    },
    {
      "id": 42399924,
      "recap_documents": [
        {
          "id": 44652530,
          "absolute_url": "/docket/7635495/34/charles-marvin-graham-iv/",
          "date_created": "2018-11-05T17:23:29.769707Z",
          "date_modified": "2018-11-05T17:23:29.772818Z",
          "sha1": "",
          "page_count": null,
          "file_size": null,
          "filepath_local": null,
          "filepath_ia": "",
          "ia_upload_failure_count": null,
          "thumbnail": null,
          "thumbnail_status": 0,
          "ocr_status": null,
          "date_upload": null,
          "document_number": "34",
          "attachment_number": null,
          "pacer_doc_id": "14604776481",
          "is_available": false,
          "is_free_on_pacer": null,
          "is_sealed": null,
          "document_type": 1,
          "description": "Wage Deduction Order"
        }
      ],
      "date_created": "2018-11-05T17:23:29.761765Z",
      "date_modified": "2018-11-05T17:23:29.763349Z",
      "date_filed": "2018-11-05",
      "entry_number": 34,
      "recap_sequence_number": "2018-11-05.001",
      "pacer_sequence_number": null,
      "description": ""
    },
    {
      "id": 43642668,
      "recap_documents": [
        {
          "id": 45906080,
          "absolute_url": "/docket/7635495/35/charles-marvin-graham-iv/",
          "date_created": "2018-11-19T18:21:18.451839Z",
          "date_modified": "2018-11-19T18:21:18.454823Z",
          "sha1": "",
          "page_count": null,
          "file_size": null,
          "filepath_local": null,
          "filepath_ia": "",
          "ia_upload_failure_count": null,
          "thumbnail": null,
          "thumbnail_status": 0,
          "ocr_status": null,
          "date_upload": null,
          "document_number": "35",
          "attachment_number": null,
          "pacer_doc_id": "14604782944",
          "is_available": false,
          "is_free_on_pacer": null,
          "is_sealed": null,
          "document_type": 1,
          "description": "Request for Entry of Order"
        }
      ],
      "date_created": "2018-11-19T18:21:18.445732Z",
      "date_modified": "2018-11-19T18:21:18.446635Z",
      "date_filed": "2018-11-19",
      "entry_number": 35,
      "recap_sequence_number": "2018-11-19.001",
      "pacer_sequence_number": null,
      "description": ""
    },
    {
      "id": 43684333,
      "recap_documents": [
        {
          "id": 45948063,
          "absolute_url": "/docket/7635495/36/charles-marvin-graham-iv/",
          "date_created": "2018-11-19T22:22:33.071616Z",
          "date_modified": "2018-11-19T22:22:33.075296Z",
          "sha1": "",
          "page_count": null,
          "file_size": null,
          "filepath_local": null,
          "filepath_ia": "",
          "ia_upload_failure_count": null,
          "thumbnail": null,
          "thumbnail_status": 0,
          "ocr_status": null,
          "date_upload": null,
          "document_number": "36",
          "attachment_number": null,
          "pacer_doc_id": "14604783196",
          "is_available": false,
          "is_free_on_pacer": null,
          "is_sealed": null,
          "document_type": 1,
          "description": "Avoid Lien"
        }
      ],
      "date_created": "2018-11-19T22:22:33.064747Z",
      "date_modified": "2018-11-19T22:22:33.066489Z",
      "date_filed": "2018-11-19",
      "entry_number": 36,
      "recap_sequence_number": "2018-11-19.001",
      "pacer_sequence_number": null,
      "description": ""
    },
    {
      "id": 49351185,
      "recap_documents": [
        {
          "id": 52852114,
          "absolute_url": "/docket/7635495/40/charles-marvin-graham-iv/",
          "date_created": "2018-12-16T21:24:10.400755Z",
          "date_modified": "2018-12-16T21:24:10.403516Z",
          "sha1": "",
          "page_count": null,
          "file_size": null,
          "filepath_local": null,
          "filepath_ia": "",
          "ia_upload_failure_count": null,
          "thumbnail": null,
          "thumbnail_status": 0,
          "ocr_status": null,
          "date_upload": null,
          "document_number": "40",
          "attachment_number": null,
          "pacer_doc_id": "14604795371",
          "is_available": false,
          "is_free_on_pacer": null,
          "is_sealed": null,
          "document_type": 1,
          "description": "Request for Entry of Order"
        }
      ],
      "date_created": "2018-12-16T21:24:10.394633Z",
      "date_modified": "2018-12-16T21:24:10.395844Z",
      "date_filed": "2018-12-16",
      "entry_number": 40,
      "recap_sequence_number": "2018-12-16.001",
      "pacer_sequence_number": 116,
      "description": ""
    },
    {
      "id": 49351183,
      "recap_documents": [
        {
          "id": 52852112,
          "absolute_url": "/docket/7635495/41/charles-marvin-graham-iv/",
          "date_created": "2018-12-16T21:24:10.375232Z",
          "date_modified": "2018-12-16T21:24:10.378039Z",
          "sha1": "",
          "page_count": null,
          "file_size": null,
          "filepath_local": null,
          "filepath_ia": "",
          "ia_upload_failure_count": null,
          "thumbnail": null,
          "thumbnail_status": 0,
          "ocr_status": null,
          "date_upload": null,
          "document_number": "41",
          "attachment_number": null,
          "pacer_doc_id": "14604795374",
          "is_available": false,
          "is_free_on_pacer": null,
          "is_sealed": null,
          "document_type": 1,
          "description": "Request for Entry of Order"
        }
      ],
      "date_created": "2018-12-16T21:24:10.369270Z",
      "date_modified": "2018-12-16T21:24:10.370397Z",
      "date_filed": "2018-12-16",
      "entry_number": 41,
      "recap_sequence_number": "2018-12-16.001",
      "pacer_sequence_number": 119,
      "description": ""
    },
    {
      "id": 49351182,
      "recap_documents": [
        {
          "id": 52852111,
          "absolute_url": "/docket/7635495/42/charles-marvin-graham-iv/",
          "date_created": "2018-12-16T21:24:10.345644Z",
          "date_modified": "2018-12-16T21:24:10.348475Z",
          "sha1": "",
          "page_count": null,
          "file_size": null,
          "filepath_local": null,
          "filepath_ia": "",
          "ia_upload_failure_count": null,
          "thumbnail": null,
          "thumbnail_status": 0,
          "ocr_status": null,
          "date_upload": null,
          "document_number": "42",
          "attachment_number": null,
          "pacer_doc_id": "14604795377",
          "is_available": false,
          "is_free_on_pacer": null,
          "is_sealed": null,
          "document_type": 1,
          "description": "Request for Entry of Order"
        }
      ],
      "date_created": "2018-12-16T21:24:10.337315Z",
      "date_modified": "2018-12-16T21:24:10.340151Z",
      "date_filed": "2018-12-16",
      "entry_number": 42,
      "recap_sequence_number": "2018-12-16.001",
      "pacer_sequence_number": 122,
      "description": ""
    },
    {
      "id": 49351180,
      "recap_documents": [
        {
          "id": 52852109,
          "absolute_url": "/docket/7635495/43/charles-marvin-graham-iv/",
          "date_created": "2018-12-16T21:24:10.311866Z",
          "date_modified": "2018-12-16T21:24:10.314670Z",
          "sha1": "",
          "page_count": null,
          "file_size": null,
          "filepath_local": null,
          "filepath_ia": "",
          "ia_upload_failure_count": null,
          "thumbnail": null,
          "thumbnail_status": 0,
          "ocr_status": null,
          "date_upload": null,
          "document_number": "43",
          "attachment_number": null,
          "pacer_doc_id": "14604795380",
          "is_available": false,
          "is_free_on_pacer": null,
          "is_sealed": null,
          "document_type": 1,
          "description": "Request for Entry of Order"
        }
      ],
      "date_created": "2018-12-16T21:24:10.303080Z",
      "date_modified": "2018-12-16T21:24:10.305554Z",
      "date_filed": "2018-12-16",
      "entry_number": 43,
      "recap_sequence_number": "2018-12-16.001",
      "pacer_sequence_number": 125,
      "description": ""
    },
    {
      "id": 49351178,
      "recap_documents": [
        {
          "id": 52852107,
          "absolute_url": "/docket/7635495/44/charles-marvin-graham-iv/",
          "date_created": "2018-12-16T21:24:10.280783Z",
          "date_modified": "2018-12-16T21:24:10.283515Z",
          "sha1": "",
          "page_count": null,
          "file_size": null,
          "filepath_local": null,
          "filepath_ia": "",
          "ia_upload_failure_count": null,
          "thumbnail": null,
          "thumbnail_status": 0,
          "ocr_status": null,
          "date_upload": null,
          "document_number": "44",
          "attachment_number": null,
          "pacer_doc_id": "14604795383",
          "is_available": false,
          "is_free_on_pacer": null,
          "is_sealed": null,
          "document_type": 1,
          "description": "Request for Entry of Order"
        }
      ],
      "date_created": "2018-12-16T21:24:10.274593Z",
      "date_modified": "2018-12-16T21:24:10.275830Z",
      "date_filed": "2018-12-16",
      "entry_number": 44,
      "recap_sequence_number": "2018-12-16.001",
      "pacer_sequence_number": 128,
      "description": ""
    },
    {
      "id": 49545536,
      "recap_documents": [
        {
          "id": 53048227,
          "absolute_url": "/docket/7635495/45/charles-marvin-graham-iv/",
          "date_created": "2018-12-18T15:20:48.254788Z",
          "date_modified": "2018-12-18T15:20:48.257641Z",
          "sha1": "",
          "page_count": null,
          "file_size": null,
          "filepath_local": null,
          "filepath_ia": "",
          "ia_upload_failure_count": null,
          "thumbnail": null,
          "thumbnail_status": 0,
          "ocr_status": null,
          "date_upload": null,
          "document_number": "45",
          "attachment_number": null,
          "pacer_doc_id": "14604796141",
          "is_available": false,
          "is_free_on_pacer": null,
          "is_sealed": null,
          "document_type": 1,
          "description": "Objection to Claim"
        }
      ],
      "date_created": "2018-12-18T15:20:48.248332Z",
      "date_modified": "2018-12-18T15:20:48.249170Z",
      "date_filed": "2018-12-18",
      "entry_number": 45,
      "recap_sequence_number": "2018-12-18.001",
      "pacer_sequence_number": 131,
      "description": ""
    },
    {
      "id": 49545524,
      "recap_documents": [
        {
          "id": 53048216,
          "absolute_url": "/docket/7635495/46/charles-marvin-graham-iv/",
          "date_created": "2018-12-18T15:20:48.190427Z",
          "date_modified": "2018-12-18T15:20:48.192618Z",
          "sha1": "",
          "page_count": null,
          "file_size": null,
          "filepath_local": null,
          "filepath_ia": "",
          "ia_upload_failure_count": null,
          "thumbnail": null,
          "thumbnail_status": 0,
          "ocr_status": null,
          "date_upload": null,
          "document_number": "46",
          "attachment_number": null,
          "pacer_doc_id": "14604796153",
          "is_available": false,
          "is_free_on_pacer": null,
          "is_sealed": null,
          "document_type": 1,
          "description": "Objection to Claim"
        }
      ],
      "date_created": "2018-12-18T15:20:48.185192Z",
      "date_modified": "2018-12-18T15:20:48.186111Z",
      "date_filed": "2018-12-18",
      "entry_number": 46,
      "recap_sequence_number": "2018-12-18.001",
      "pacer_sequence_number": 135,
      "description": ""
    },
    {
      "id": 49580037,
      "recap_documents": [
        {
          "id": 53082868,
          "absolute_url": "/docket/7635495/47/charles-marvin-graham-iv/",
          "date_created": "2018-12-18T18:21:30.404986Z",
          "date_modified": "2018-12-18T18:21:30.407645Z",
          "sha1": "",
          "page_count": null,
          "file_size": null,
          "filepath_local": null,
          "filepath_ia": "",
          "ia_upload_failure_count": null,
          "thumbnail": null,
          "thumbnail_status": 0,
          "ocr_status": null,
          "date_upload": null,
          "document_number": "47",
          "attachment_number": null,
          "pacer_doc_id": "14604796310",
          "is_available": false,
          "is_free_on_pacer": null,
          "is_sealed": null,
          "document_type": 1,
          "description": "Objection to Claim"
        }
      ],
      "date_created": "2018-12-18T18:21:30.398449Z",
      "date_modified": "2018-12-18T18:21:30.399363Z",
      "date_filed": "2018-12-18",
      "entry_number": 47,
      "recap_sequence_number": "2018-12-18.001",
      "pacer_sequence_number": 139,
      "description": ""
    },
    {
      "id": 49580032,
      "recap_documents": [
        {
          "id": 53082862,
          "absolute_url": "/docket/7635495/48/charles-marvin-graham-iv/",
          "date_created": "2018-12-18T18:21:30.373643Z",
          "date_modified": "2018-12-18T18:21:30.375950Z",
          "sha1": "",
          "page_count": null,
          "file_size": null,
          "filepath_local": null,
          "filepath_ia": "",
          "ia_upload_failure_count": null,
          "thumbnail": null,
          "thumbnail_status": 0,
          "ocr_status": null,
          "date_upload": null,
          "document_number": "48",
          "attachment_number": null,
          "pacer_doc_id": "14604796313",
          "is_available": false,
          "is_free_on_pacer": null,
          "is_sealed": null,
          "document_type": 1,
          "description": "Request for Entry of Order"
        }
      ],
      "date_created": "2018-12-18T18:21:30.367886Z",
      "date_modified": "2018-12-18T18:21:30.368651Z",
      "date_filed": "2018-12-18",
      "entry_number": 48,
      "recap_sequence_number": "2018-12-18.001",
      "pacer_sequence_number": 145,
      "description": ""
    },
    {
      "id": 49606076,
      "recap_documents": [
        {
          "id": 53109154,
          "absolute_url": "/docket/7635495/49/charles-marvin-graham-iv/",
          "date_created": "2018-12-18T20:25:18.522880Z",
          "date_modified": "2018-12-18T20:25:18.525934Z",
          "sha1": "",
          "page_count": null,
          "file_size": null,
          "filepath_local": null,
          "filepath_ia": "",
          "ia_upload_failure_count": null,
          "thumbnail": null,
          "thumbnail_status": 0,
          "ocr_status": null,
          "date_upload": null,
          "document_number": "49",
          "attachment_number": null,
          "pacer_doc_id": "14604796468",
          "is_available": false,
          "is_free_on_pacer": null,
          "is_sealed": null,
          "document_type": 1,
          "description": "Objection to Claim"
        }
      ],
      "date_created": "2018-12-18T20:25:18.515782Z",
      "date_modified": "2018-12-18T20:25:18.517155Z",
      "date_filed": "2018-12-18",
      "entry_number": 49,
      "recap_sequence_number": "2018-12-18.001",
      "pacer_sequence_number": 148,
      "description": ""
    },
    {
      "id": 49720450,
      "recap_documents": [
        {
          "id": 53224589,
          "absolute_url": "/docket/7635495//charles-marvin-graham-iv/",
          "date_created": "2018-12-19T18:23:18.443202Z",
          "date_modified": "2018-12-19T18:23:18.446619Z",
          "sha1": "",
          "page_count": null,
          "file_size": null,
          "filepath_local": null,
          "filepath_ia": "",
          "ia_upload_failure_count": null,
          "thumbnail": null,
          "thumbnail_status": 0,
          "ocr_status": null,
          "date_upload": null,
          "document_number": "",
          "attachment_number": null,
          "pacer_doc_id": "",
          "is_available": false,
          "is_free_on_pacer": null,
          "is_sealed": null,
          "document_type": 1,
          "description": "Objection to Claim"
        }
      ],
      "date_created": "2018-12-19T18:23:18.432248Z",
      "date_modified": "2018-12-19T18:23:18.432277Z",
      "date_filed": "2018-12-19",
      "entry_number": null,
      "recap_sequence_number": "2018-12-19.001",
      "pacer_sequence_number": null,
      "description": ""
    },
    {
      "id": 64511014,
      "recap_documents": [
        {
          "id": 68643157,
          "absolute_url": "/docket/7635495/65/charles-marvin-graham-iv/",
          "date_created": "2019-05-03T07:02:16.102775Z",
          "date_modified": "2019-05-03T07:02:16.106580Z",
          "sha1": "",
          "page_count": null,
          "file_size": null,
          "filepath_local": null,
          "filepath_ia": "",
          "ia_upload_failure_count": null,
          "thumbnail": null,
          "thumbnail_status": 0,
          "ocr_status": null,
          "date_upload": null,
          "document_number": "65",
          "attachment_number": null,
          "pacer_doc_id": "14604863982",
          "is_available": false,
          "is_free_on_pacer": null,
          "is_sealed": null,
          "document_type": 1,
          "description": "BNC Certificate of Mailing "
        }
      ],
      "date_created": "2019-05-03T07:02:16.094981Z",
      "date_modified": "2019-05-03T07:02:16.096260Z",
      "date_filed": "2019-05-03",
      "entry_number": 65,
      "recap_sequence_number": "2019-05-03.001",
      "pacer_sequence_number": 204,
      "description": ""
    },
    {
      "id": 94496128,
      "recap_documents": [
        {
          "id": 98697224,
          "absolute_url": "/docket/7635495/67/charles-marvin-graham-iv/",
          "date_created": "2019-07-11T15:22:09.853724Z",
          "date_modified": "2019-07-11T15:22:09.856154Z",
          "sha1": "",
          "page_count": null,
          "file_size": null,
          "filepath_local": null,
          "filepath_ia": "",
          "ia_upload_failure_count": null,
          "thumbnail": null,
          "thumbnail_status": 0,
          "ocr_status": null,
          "date_upload": null,
          "document_number": "67",
          "attachment_number": null,
          "pacer_doc_id": "14604901601",
          "is_available": false,
          "is_free_on_pacer": null,
          "is_sealed": null,
          "document_type": 1,
          "description": "Creditor Request for Notices"
        }
      ],
      "date_created": "2019-07-11T15:22:09.846336Z",
      "date_modified": "2019-07-11T15:22:09.847541Z",
      "date_filed": "2019-07-11",
      "entry_number": 67,
      "recap_sequence_number": "2019-07-11.001",
      "pacer_sequence_number": 211,
      "description": ""
    },
    {
      "id": 94566820,
      "recap_documents": [
        {
          "id": 98768438,
          "absolute_url": "/docket/7635495/68/charles-marvin-graham-iv/",
          "date_created": "2019-07-11T20:22:31.672439Z",
          "date_modified": "2019-07-11T20:22:31.676744Z",
          "sha1": "",
          "page_count": null,
          "file_size": null,
          "filepath_local": null,
          "filepath_ia": "",
          "ia_upload_failure_count": null,
          "thumbnail": null,
          "thumbnail_status": 0,
          "ocr_status": null,
          "date_upload": null,
          "document_number": "68",
          "attachment_number": null,
          "pacer_doc_id": "14604902122",
          "is_available": false,
          "is_free_on_pacer": null,
          "is_sealed": null,
          "document_type": 1,
          "description": "Dismiss Case"
        }
      ],
      "date_created": "2019-07-11T20:22:31.664930Z",
      "date_modified": "2019-07-11T20:22:31.666161Z",
      "date_filed": "2019-07-11",
      "entry_number": 68,
      "recap_sequence_number": "2019-07-11.001",
      "pacer_sequence_number": 213,
      "description": ""
    },
    {
      "id": 95900791,
      "recap_documents": [
        {
          "id": 100113735,
          "absolute_url": "/docket/7635495/69/charles-marvin-graham-iv/",
          "date_created": "2019-07-23T17:49:32.704624Z",
          "date_modified": "2019-07-23T17:49:32.707764Z",
          "sha1": "",
          "page_count": null,
          "file_size": null,
          "filepath_local": null,
          "filepath_ia": "",
          "ia_upload_failure_count": null,
          "thumbnail": null,
          "thumbnail_status": 0,
          "ocr_status": null,
          "date_upload": null,
          "document_number": "69",
          "attachment_number": null,
          "pacer_doc_id": "14604907847",
          "is_available": false,
          "is_free_on_pacer": null,
          "is_sealed": null,
          "document_type": 1,
          "description": "Objection"
        }
      ],
      "date_created": "2019-07-23T17:49:32.695996Z",
      "date_modified": "2019-07-23T17:49:32.697320Z",
      "date_filed": "2019-07-23",
      "entry_number": 69,
      "recap_sequence_number": "2019-07-23.001",
      "pacer_sequence_number": 215,
      "description": ""
    }
  ],
  "parties": [],
  "original_court_info": null,
  "bankruptcy_information": null,
  "claims": [],
  "idb_data": null,
  "absolute_url": "/docket/7635495/charles-marvin-graham-iv/",
  "source": 1,
  "appeal_from_str": "",
  "assigned_to_str": "",
  "referred_to_str": "",
  "panel_str": "",
  "date_created": "2018-08-10T04:23:25.654388Z",
  "date_modified": "2019-07-23T17:49:32.688248Z",
  "date_last_index": null,
  "date_cert_granted": null,
  "date_cert_denied": null,
  "date_argued": null,
  "date_reargued": null,
  "date_reargument_denied": null,
  "date_filed": null,
  "date_terminated": null,
  "date_last_filing": null,
  "case_name_short": "",
  "case_name": "Charles Marvin Graham, IV",
  "case_name_full": "",
  "slug": "charles-marvin-graham-iv",
  "docket_number": "18-11611",
  "docket_number_core": "",
  "pacer_case_id": "146519",
  "cause": "",
  "nature_of_suit": "",
  "jury_demand": "",
  "jurisdiction_type": "",
  "appellate_fee_status": "",
  "appellate_case_type_information": "",
  "mdl_status": "",
  "filepath_local": null,
  "filepath_ia": "",
  "filepath_ia_json": "https://archive.org/download/gov.uscourts.oknb.146519/gov.uscourts.oknb.146519.docket.json",
  "date_blocked": "2018-08-09",
  "blocked": true,
  "court": "oknb",
  "appeal_from": null,
  "assigned_to": null,
  "referred_to": null,
  "panel": []
}