{
  "id": 14847013,
  "docket_entries": [
    {
      "id": 60391191,
      "recap_documents": [
        {
          "id": 64493362,
          "absolute_url": "/docket/14847013/1/barbara-smith/",
          "date_created": "2019-04-01T15:17:44.316211Z",
          "date_modified": "2019-04-01T15:17:44.318701Z",
          "sha1": "",
          "page_count": null,
          "file_size": null,
          "filepath_local": null,
          "filepath_ia": "",
          "ia_upload_failure_count": null,
          "thumbnail": null,
          "thumbnail_status": 0,
          "ocr_status": null,
          "date_upload": null,
          "document_number": "1",
          "attachment_number": null,
          "pacer_doc_id": "126019745193",
          "is_available": false,
          "is_free_on_pacer": null,
          "is_sealed": null,
          "document_type": 1,
          "description": "Voluntary Petition (Chapter 13)"
        }
      ],
      "date_created": "2019-04-01T15:17:44.308594Z",
      "date_modified": "2019-04-01T15:17:44.309671Z",
      "date_filed": "2019-04-01",
      "entry_number": 1,
      "recap_sequence_number": "2019-04-01.001",
      "pacer_sequence_number": 2,
      "description": ""
    },
    {
      "id": 60405301,
      "recap_documents": [
        {
          "id": 64507557,
          "absolute_url": "/docket/14847013/2/barbara-smith/",
          "date_created": "2019-04-01T16:20:28.824441Z",
          "date_modified": "2019-04-01T16:20:28.830063Z",
          "sha1": "",
          "page_count": null,
          "file_size": null,
          "filepath_local": null,
          "filepath_ia": "",
          "ia_upload_failure_count": null,
          "thumbnail": null,
          "thumbnail_status": 0,
          "ocr_status": null,
          "date_upload": null,
          "document_number": "2",
          "attachment_number": null,
          "pacer_doc_id": "126019745211",
          "is_available": false,
          "is_free_on_pacer": null,
          "is_sealed": null,
          "document_type": 1,
          "description": "Certificate of Credit Counseling"
        }
      ],
      "date_created": "2019-04-01T16:20:28.817838Z",
      "date_modified": "2019-04-01T16:20:28.819228Z",
      "date_filed": "2019-04-01",
      "entry_number": 2,
      "recap_sequence_number": "2019-04-01.001",
      "pacer_sequence_number": 7,
      "description": ""
    },
    {
      "id": 60405227,
      "recap_documents": [
        {
          "id": 64507483,
          "absolute_url": "/docket/14847013/3/barbara-smith/",
          "date_created": "2019-04-01T16:20:28.484140Z",
          "date_modified": "2019-04-01T16:20:28.512694Z",
          "sha1": "",
          "page_count": null,
          "file_size": null,
          "filepath_local": null,
          "filepath_ia": "",
          "ia_upload_failure_count": null,
          "thumbnail": null,
          "thumbnail_status": 0,
          "ocr_status": null,
          "date_upload": null,
          "document_number": "3",
          "attachment_number": null,
          "pacer_doc_id": "126019745229",
          "is_available": false,
          "is_free_on_pacer": null,
          "is_sealed": null,
          "document_type": 1,
          "description": "Application for Loss Mitigation"
        }
      ],
      "date_created": "2019-04-01T16:20:28.477839Z",
      "date_modified": "2019-04-01T16:20:28.507678Z",
      "date_filed": "2019-04-01",
      "entry_number": 3,
      "recap_sequence_number": "2019-04-01.001",
      "pacer_sequence_number": 9,
      "description": ""
    },
    {
      "id": 60550285,
      "recap_documents": [
        {
          "id": 64653631,
          "absolute_url": "/docket/14847013/4/barbara-smith/",
          "date_created": "2019-04-02T15:13:23.324294Z",
          "date_modified": "2019-04-02T15:13:23.326425Z",
          "sha1": "",
          "page_count": null,
          "file_size": null,
          "filepath_local": null,
          "filepath_ia": "",
          "ia_upload_failure_count": null,
          "thumbnail": null,
          "thumbnail_status": 0,
          "ocr_status": null,
          "date_upload": null,
          "document_number": "4",
          "attachment_number": null,
          "pacer_doc_id": "126019748545",
          "is_available": false,
          "is_free_on_pacer": null,
          "is_sealed": null,
          "document_type": 1,
          "description": "341(a) Notice (Chapter 13) (BNC)"
        }
      ],
      "date_created": "2019-04-02T15:13:23.319202Z",
      "date_modified": "2019-04-02T15:13:23.319861Z",
      "date_filed": "2019-04-02",
      "entry_number": 4,
      "recap_sequence_number": "2019-04-02.001",
      "pacer_sequence_number": 15,
      "description": ""
    },
    {
      "id": 60550299,
      "recap_documents": [
        {
          "id": 64653645,
          "absolute_url": "/docket/14847013//barbara-smith/",
          "date_created": "2019-04-02T15:13:23.726517Z",
          "date_modified": "2019-04-02T15:13:23.728521Z",
          "sha1": "",
          "page_count": null,
          "file_size": null,
          "filepath_local": null,
          "filepath_ia": "",
          "ia_upload_failure_count": null,
          "thumbnail": null,
          "thumbnail_status": 0,
          "ocr_status": null,
          "date_upload": null,
          "document_number": "",
          "attachment_number": null,
          "pacer_doc_id": "",
          "is_available": false,
          "is_free_on_pacer": null,
          "is_sealed": null,
          "document_type": 1,
          "description": "Repeat Filer"
        }
      ],
      "date_created": "2019-04-02T15:13:23.722766Z",
      "date_modified": "2019-04-02T15:13:23.722788Z",
      "date_filed": "2019-04-02",
      "entry_number": null,
      "recap_sequence_number": "2019-04-02.001",
      "pacer_sequence_number": null,
      "description": ""
    },
    {
      "id": 60885475,
      "recap_documents": [
        {
          "id": 64991759,
          "absolute_url": "/docket/14847013/5/barbara-smith/",
          "date_created": "2019-04-04T15:16:07.331066Z",
          "date_modified": "2019-04-04T15:16:07.336116Z",
          "sha1": "",
          "page_count": null,
          "file_size": null,
          "filepath_local": null,
          "filepath_ia": "",
          "ia_upload_failure_count": null,
          "thumbnail": null,
          "thumbnail_status": 0,
          "ocr_status": null,
          "date_upload": null,
          "document_number": "5",
          "attachment_number": null,
          "pacer_doc_id": "126019756065",
          "is_available": false,
          "is_free_on_pacer": null,
          "is_sealed": null,
          "document_type": 1,
          "description": "Notice, Appearance"
        }
      ],
      "date_created": "2019-04-04T15:16:07.319725Z",
      "date_modified": "2019-04-04T15:16:07.321523Z",
      "date_filed": "2019-04-04",
      "entry_number": 5,
      "recap_sequence_number": "2019-04-04.001",
      "pacer_sequence_number": 17,
      "description": ""
    },
    {
      "id": 61012670,
      "recap_documents": [
        {
          "id": 65119774,
          "absolute_url": "/docket/14847013/6/barbara-smith/",
          "date_created": "2019-04-05T05:13:19.579929Z",
          "date_modified": "2019-04-05T05:13:19.583228Z",
          "sha1": "",
          "page_count": null,
          "file_size": null,
          "filepath_local": null,
          "filepath_ia": "",
          "ia_upload_failure_count": null,
          "thumbnail": null,
          "thumbnail_status": 0,
          "ocr_status": null,
          "date_upload": null,
          "document_number": "6",
          "attachment_number": null,
          "pacer_doc_id": "126019758747",
          "is_available": false,
          "is_free_on_pacer": null,
          "is_sealed": null,
          "document_type": 1,
          "description": "Certificate of Mailing - 341(a) Meeting"
        }
      ],
      "date_created": "2019-04-05T05:13:19.572181Z",
      "date_modified": "2019-04-05T05:13:19.573208Z",
      "date_filed": "2019-04-05",
      "entry_number": 6,
      "recap_sequence_number": "2019-04-05.001",
      "pacer_sequence_number": 21,
      "description": ""
    },
    {
      "id": 64835453,
      "recap_documents": [
        {
          "id": 68969574,
          "absolute_url": "/docket/14847013//barbara-smith/",
          "date_created": "2019-05-06T20:07:35.842115Z",
          "date_modified": "2019-05-06T20:07:35.845262Z",
          "sha1": "",
          "page_count": null,
          "file_size": null,
          "filepath_local": null,
          "filepath_ia": "",
          "ia_upload_failure_count": null,
          "thumbnail": null,
          "thumbnail_status": 0,
          "ocr_status": null,
          "date_upload": null,
          "document_number": "",
          "attachment_number": null,
          "pacer_doc_id": "",
          "is_available": false,
          "is_free_on_pacer": null,
          "is_sealed": null,
          "document_type": 1,
          "description": "Statement Adjourning Meeting of Creditors"
        }
      ],
      "date_created": "2019-05-06T20:07:35.837025Z",
      "date_modified": "2019-05-06T20:07:35.837045Z",
      "date_filed": "2019-05-06",
      "entry_number": null,
      "recap_sequence_number": "2019-05-06.001",
      "pacer_sequence_number": null,
      "description": ""
    },
    {
      "id": 83962463,
      "recap_documents": [
        {
          "id": 88112392,
          "absolute_url": "/docket/14847013/8/barbara-smith/",
          "date_created": "2019-05-21T16:23:59.153413Z",
          "date_modified": "2019-05-21T16:23:59.156022Z",
          "sha1": "",
          "page_count": null,
          "file_size": null,
          "filepath_local": null,
          "filepath_ia": "",
          "ia_upload_failure_count": null,
          "thumbnail": null,
          "thumbnail_status": 0,
          "ocr_status": null,
          "date_upload": null,
          "document_number": "8",
          "attachment_number": null,
          "pacer_doc_id": "126019901553",
          "is_available": false,
          "is_free_on_pacer": null,
          "is_sealed": null,
          "document_type": 1,
          "description": "Motion, Dismiss Case"
        }
      ],
      "date_created": "2019-05-21T16:23:59.147323Z",
      "date_modified": "2019-05-21T16:23:59.148460Z",
      "date_filed": "2019-05-21",
      "entry_number": 8,
      "recap_sequence_number": "2019-05-21.001",
      "pacer_sequence_number": 26,
      "description": ""
    },
    {
      "id": 85206813,
      "recap_documents": [
        {
          "id": 89366515,
          "absolute_url": "/docket/14847013/9/barbara-smith/",
          "date_created": "2019-05-31T17:21:51.860642Z",
          "date_modified": "2019-05-31T17:21:51.865405Z",
          "sha1": "",
          "page_count": null,
          "file_size": null,
          "filepath_local": null,
          "filepath_ia": "",
          "ia_upload_failure_count": null,
          "thumbnail": null,
          "thumbnail_status": 0,
          "ocr_status": null,
          "date_upload": null,
          "document_number": "9",
          "attachment_number": null,
          "pacer_doc_id": "126019930895",
          "is_available": false,
          "is_free_on_pacer": null,
          "is_sealed": null,
          "document_type": 1,
          "description": "Objection, Confirmation of Plan"
        }
      ],
      "date_created": "2019-05-31T17:21:51.851364Z",
      "date_modified": "2019-05-31T17:21:51.852715Z",
      "date_filed": "2019-05-31",
      "entry_number": 9,
      "recap_sequence_number": "2019-05-31.001",
      "pacer_sequence_number": 29,
      "description": ""
    },
    {
      "id": 86746434,
      "recap_documents": [
        {
          "id": 90918955,
          "absolute_url": "/docket/14847013//barbara-smith/",
          "date_created": "2019-06-14T12:16:24.327687Z",
          "date_modified": "2019-06-14T12:16:24.332540Z",
          "sha1": "",
          "page_count": null,
          "file_size": null,
          "filepath_local": null,
          "filepath_ia": "",
          "ia_upload_failure_count": null,
          "thumbnail": null,
          "thumbnail_status": 0,
          "ocr_status": null,
          "date_upload": null,
          "document_number": "",
          "attachment_number": null,
          "pacer_doc_id": "126019973407",
          "is_available": false,
          "is_free_on_pacer": null,
          "is_sealed": null,
          "document_type": 1,
          "description": "Notice of Mortgage Payment Change (Rule 3002.1)"
        }
      ],
      "date_created": "2019-06-14T12:16:24.319832Z",
      "date_modified": "2019-06-14T12:16:24.319866Z",
      "date_filed": "2019-06-14",
      "entry_number": null,
      "recap_sequence_number": "2019-06-14.001",
      "pacer_sequence_number": 33,
      "description": ""
    },
    {
      "id": 95713931,
      "recap_documents": [
        {
          "id": 99925240,
          "absolute_url": "/docket/14847013/10/barbara-smith/",
          "date_created": "2019-07-22T15:21:39.047370Z",
          "date_modified": "2019-07-22T15:21:39.051116Z",
          "sha1": "",
          "page_count": null,
          "file_size": null,
          "filepath_local": null,
          "filepath_ia": "",
          "ia_upload_failure_count": null,
          "thumbnail": null,
          "thumbnail_status": 0,
          "ocr_status": null,
          "date_upload": null,
          "document_number": "10",
          "attachment_number": null,
          "pacer_doc_id": "126020068696",
          "is_available": false,
          "is_free_on_pacer": null,
          "is_sealed": null,
          "document_type": 1,
          "description": "Motion, Dismiss Case"
        }
      ],
      "date_created": "2019-07-22T15:21:39.039855Z",
      "date_modified": "2019-07-22T15:21:39.040652Z",
      "date_filed": "2019-07-22",
      "entry_number": 10,
      "recap_sequence_number": "2019-07-22.001",
      "pacer_sequence_number": 35,
      "description": ""
    },
    {
      "id": 96128964,
      "recap_documents": [
        {
          "id": 100343637,
          "absolute_url": "/docket/14847013/11/barbara-smith/",
          "date_created": "2019-07-25T04:27:25.969387Z",
          "date_modified": "2019-07-25T04:27:25.972355Z",
          "sha1": "",
          "page_count": null,
          "file_size": null,
          "filepath_local": null,
          "filepath_ia": "",
          "ia_upload_failure_count": null,
          "thumbnail": null,
          "thumbnail_status": 0,
          "ocr_status": null,
          "date_upload": null,
          "document_number": "11",
          "attachment_number": null,
          "pacer_doc_id": "126020078878",
          "is_available": false,
          "is_free_on_pacer": null,
          "is_sealed": null,
          "document_type": 1,
          "description": "Certificate of Mailing - Order to Dismiss"
        }
      ],
      "date_created": "2019-07-25T04:27:25.962160Z",
      "date_modified": "2019-07-25T04:27:25.963682Z",
      "date_filed": "2019-07-25",
      "entry_number": 11,
      "recap_sequence_number": "2019-07-25.001",
      "pacer_sequence_number": 38,
      "description": ""
    },
    {
      "id": 98440862,
      "recap_documents": [
        {
          "id": 102672978,
          "absolute_url": "/docket/14847013/12/barbara-smith/",
          "date_created": "2019-08-13T18:22:10.838874Z",
          "date_modified": "2019-08-13T18:22:10.842980Z",
          "sha1": "",
          "page_count": null,
          "file_size": null,
          "filepath_local": null,
          "filepath_ia": "",
          "ia_upload_failure_count": null,
          "thumbnail": null,
          "thumbnail_status": 0,
          "ocr_status": null,
          "date_upload": null,
          "document_number": "12",
          "attachment_number": null,
          "pacer_doc_id": "126020133251",
          "is_available": false,
          "is_free_on_pacer": null,
          "is_sealed": null,
          "document_type": 1,
          "description": "Chapter 13 Trustee's Final Report and Account"
        }
      ],
      "date_created": "2019-08-13T18:22:10.828050Z",
      "date_modified": "2019-08-13T18:22:10.829615Z",
      "date_filed": "2019-08-13",
      "entry_number": 12,
      "recap_sequence_number": "2019-08-13.001",
      "pacer_sequence_number": 40,
      "description": ""
    },
    {
      "id": 99427872,
      "recap_documents": [
        {
          "id": 103667288,
          "absolute_url": "/docket/14847013/13/barbara-smith/",
          "date_created": "2019-08-21T20:07:56.442608Z",
          "date_modified": "2019-08-21T20:07:56.446450Z",
          "sha1": "",
          "page_count": null,
          "file_size": null,
          "filepath_local": null,
          "filepath_ia": "",
          "ia_upload_failure_count": null,
          "thumbnail": null,
          "thumbnail_status": 0,
          "ocr_status": null,
          "date_upload": null,
          "document_number": "13",
          "attachment_number": null,
          "pacer_doc_id": "126020154728",
          "is_available": false,
          "is_free_on_pacer": null,
          "is_sealed": null,
          "document_type": 1,
          "description": "Order Discharging Trustee (BNC)"
        }
      ],
      "date_created": "2019-08-21T20:07:56.436789Z",
      "date_modified": "2019-08-21T20:07:56.437698Z",
      "date_filed": "2019-08-21",
      "entry_number": 13,
      "recap_sequence_number": "2019-08-21.001",
      "pacer_sequence_number": 42,
      "description": ""
    },
    {
      "id": 99891219,
      "recap_documents": [
        {
          "id": 104133803,
          "absolute_url": "/docket/14847013/14/barbara-smith/",
          "date_created": "2019-08-24T05:11:51.383716Z",
          "date_modified": "2019-08-24T05:11:51.387456Z",
          "sha1": "",
          "page_count": null,
          "file_size": null,
          "filepath_local": null,
          "filepath_ia": "",
          "ia_upload_failure_count": null,
          "thumbnail": null,
          "thumbnail_status": 0,
          "ocr_status": null,
          "date_upload": null,
          "document_number": "14",
          "attachment_number": null,
          "pacer_doc_id": "126020162845",
          "is_available": false,
          "is_free_on_pacer": null,
          "is_sealed": null,
          "document_type": 1,
          "description": "Certificate of Mailing - Order Discharging Trustee"
        }
      ],
      "date_created": "2019-08-24T05:11:51.378378Z",
      "date_modified": "2019-08-24T05:11:51.379249Z",
      "date_filed": "2019-08-24",
      "entry_number": 14,
      "recap_sequence_number": "2019-08-24.001",
      "pacer_sequence_number": 44,
      "description": ""
    },
    {
      "id": 100446410,
      "recap_documents": [
        {
          "id": 104693885,
          "absolute_url": "/docket/14847013//barbara-smith/",
          "date_created": "2019-08-29T16:21:51.104978Z",
          "date_modified": "2019-08-29T16:21:51.109546Z",
          "sha1": "",
          "page_count": null,
          "file_size": null,
          "filepath_local": null,
          "filepath_ia": "",
          "ia_upload_failure_count": null,
          "thumbnail": null,
          "thumbnail_status": 0,
          "ocr_status": null,
          "date_upload": null,
          "document_number": "",
          "attachment_number": null,
          "pacer_doc_id": "",
          "is_available": false,
          "is_free_on_pacer": null,
          "is_sealed": null,
          "document_type": 1,
          "description": "Close Bankruptcy Case"
        }
      ],
      "date_created": "2019-08-29T16:21:51.097482Z",
      "date_modified": "2019-08-29T16:21:51.097523Z",
      "date_filed": "2019-08-29",
      "entry_number": null,
      "recap_sequence_number": "2019-08-29.001",
      "pacer_sequence_number": null,
      "description": ""
    }
  ],
  "parties": [],
  "original_court_info": null,
  "bankruptcy_information": null,
  "claims": [],
  "idb_data": null,
  "absolute_url": "/docket/14847013/barbara-smith/",
  "source": 1,
  "appeal_from_str": "",
  "assigned_to_str": "",
  "referred_to_str": "",
  "panel_str": "",
  "date_created": "2019-04-01T15:17:44.303660Z",
  "date_modified": "2019-08-29T16:21:51.089013Z",
  "date_last_index": null,
  "date_cert_granted": null,
  "date_cert_denied": null,
  "date_argued": null,
  "date_reargued": null,
  "date_reargument_denied": null,
  "date_filed": null,
  "date_terminated": null,
  "date_last_filing": null,
  "case_name_short": "Barbara Smith",
  "case_name": "Barbara Smith",
  "case_name_full": "",
  "slug": "barbara-smith",
  "docket_number": "19-22724",
  "docket_number_core": "",
  "pacer_case_id": "291826",
  "cause": "",
  "nature_of_suit": "",
  "jury_demand": "",
  "jurisdiction_type": "",
  "appellate_fee_status": "",
  "appellate_case_type_information": "",
  "mdl_status": "",
  "filepath_local": null,
  "filepath_ia": "",
  "filepath_ia_json": "",
  "date_blocked": "2019-04-01",
  "blocked": true,
  "court": "nysb",
  "appeal_from": null,
  "assigned_to": null,
  "referred_to": null,
  "panel": []
}