{
  "id": 14882500,
  "docket_entries": [
    {
      "id": 61039560,
      "recap_documents": [
        {
          "id": 65146914,
          "absolute_url": "/docket/14882500/39/fairfield-sentry-limited-in-liquidation-acting-v-chelsea-trust-company/",
          "date_created": "2019-04-05T13:15:55.058161Z",
          "date_modified": "2019-04-05T13:15:55.060302Z",
          "sha1": "",
          "page_count": null,
          "file_size": null,
          "filepath_local": null,
          "filepath_ia": "",
          "ia_upload_failure_count": null,
          "thumbnail": null,
          "thumbnail_status": 0,
          "ocr_status": null,
          "date_upload": null,
          "document_number": "39",
          "attachment_number": null,
          "pacer_doc_id": "126019759229",
          "is_available": false,
          "is_free_on_pacer": null,
          "is_sealed": null,
          "document_type": 1,
          "description": "So Ordered Stipulation"
        }
      ],
      "date_created": "2019-04-05T13:15:55.053204Z",
      "date_modified": "2019-04-05T13:15:55.054078Z",
      "date_filed": "2019-04-05",
      "entry_number": 39,
      "recap_sequence_number": "2019-04-05.001",
      "pacer_sequence_number": 115,
      "description": ""
    },
    {
      "id": 64925671,
      "recap_documents": [
        {
          "id": 69060885,
          "absolute_url": "/docket/14882500/40/fairfield-sentry-limited-in-liquidation-acting-v-chelsea-trust-company/",
          "date_created": "2019-05-07T15:22:40.529910Z",
          "date_modified": "2019-05-07T15:22:40.533742Z",
          "sha1": "",
          "page_count": null,
          "file_size": null,
          "filepath_local": null,
          "filepath_ia": "",
          "ia_upload_failure_count": null,
          "thumbnail": null,
          "thumbnail_status": 0,
          "ocr_status": null,
          "date_upload": null,
          "document_number": "40",
          "attachment_number": null,
          "pacer_doc_id": "126019855825",
          "is_available": false,
          "is_free_on_pacer": null,
          "is_sealed": null,
          "document_type": 1,
          "description": "Notice, Appeal (fee)"
        }
      ],
      "date_created": "2019-05-07T15:22:40.522168Z",
      "date_modified": "2019-05-07T15:22:40.523463Z",
      "date_filed": "2019-05-07",
      "entry_number": 40,
      "recap_sequence_number": "2019-05-07.001",
      "pacer_sequence_number": 117,
      "description": ""
    },
    {
      "id": 64925641,
      "recap_documents": [
        {
          "id": 69060855,
          "absolute_url": "/docket/14882500//fairfield-sentry-limited-in-liquidation-acting-v-chelsea-trust-company/",
          "date_created": "2019-05-07T15:22:40.319694Z",
          "date_modified": "2019-05-07T15:22:40.324090Z",
          "sha1": "",
          "page_count": null,
          "file_size": null,
          "filepath_local": null,
          "filepath_ia": "",
          "ia_upload_failure_count": null,
          "thumbnail": null,
          "thumbnail_status": 0,
          "ocr_status": null,
          "date_upload": null,
          "document_number": "",
          "attachment_number": null,
          "pacer_doc_id": "",
          "is_available": false,
          "is_free_on_pacer": null,
          "is_sealed": null,
          "document_type": 1,
          "description": "Auto - docket of credit card"
        }
      ],
      "date_created": "2019-05-07T15:22:40.311997Z",
      "date_modified": "2019-05-07T15:22:40.312036Z",
      "date_filed": "2019-05-07",
      "entry_number": null,
      "recap_sequence_number": "2019-05-07.001",
      "pacer_sequence_number": null,
      "description": ""
    },
    {
      "id": 83187346,
      "recap_documents": [
        {
          "id": 87333096,
          "absolute_url": "/docket/14882500/41/fairfield-sentry-limited-in-liquidation-acting-v-chelsea-trust-company/",
          "date_created": "2019-05-16T17:26:25.793482Z",
          "date_modified": "2019-05-16T17:26:25.796145Z",
          "sha1": "",
          "page_count": null,
          "file_size": null,
          "filepath_local": null,
          "filepath_ia": "",
          "ia_upload_failure_count": null,
          "thumbnail": null,
          "thumbnail_status": 0,
          "ocr_status": null,
          "date_upload": null,
          "document_number": "41",
          "attachment_number": null,
          "pacer_doc_id": "126019889320",
          "is_available": false,
          "is_free_on_pacer": null,
          "is_sealed": null,
          "document_type": 1,
          "description": "Designation of Contents (appellant)"
        }
      ],
      "date_created": "2019-05-16T17:26:25.787761Z",
      "date_modified": "2019-05-16T17:26:25.788612Z",
      "date_filed": "2019-05-16",
      "entry_number": 41,
      "recap_sequence_number": "2019-05-16.001",
      "pacer_sequence_number": 123,
      "description": ""
    },
    {
      "id": 84295928,
      "recap_documents": [
        {
          "id": 88448464,
          "absolute_url": "/docket/14882500/42/fairfield-sentry-limited-in-liquidation-acting-v-chelsea-trust-company/",
          "date_created": "2019-05-23T17:19:57.549235Z",
          "date_modified": "2019-05-23T17:19:57.553274Z",
          "sha1": "",
          "page_count": null,
          "file_size": null,
          "filepath_local": null,
          "filepath_ia": "",
          "ia_upload_failure_count": null,
          "thumbnail": null,
          "thumbnail_status": 0,
          "ocr_status": null,
          "date_upload": null,
          "document_number": "42",
          "attachment_number": null,
          "pacer_doc_id": "126019910106",
          "is_available": false,
          "is_free_on_pacer": null,
          "is_sealed": null,
          "document_type": 1,
          "description": "Civil Cover Sheet"
        }
      ],
      "date_created": "2019-05-23T17:19:57.541573Z",
      "date_modified": "2019-05-23T17:19:57.542493Z",
      "date_filed": "2019-05-23",
      "entry_number": 42,
      "recap_sequence_number": "2019-05-23.001",
      "pacer_sequence_number": 126,
      "description": ""
    },
    {
      "id": 84953594,
      "recap_documents": [
        {
          "id": 89111437,
          "absolute_url": "/docket/14882500/43/fairfield-sentry-limited-in-liquidation-acting-v-chelsea-trust-company/",
          "date_created": "2019-05-30T00:27:36.396744Z",
          "date_modified": "2019-05-30T00:27:36.400553Z",
          "sha1": "",
          "page_count": null,
          "file_size": null,
          "filepath_local": null,
          "filepath_ia": "",
          "ia_upload_failure_count": null,
          "thumbnail": null,
          "thumbnail_status": 0,
          "ocr_status": null,
          "date_upload": null,
          "document_number": "43",
          "attachment_number": null,
          "pacer_doc_id": "126019924968",
          "is_available": false,
          "is_free_on_pacer": null,
          "is_sealed": null,
          "document_type": 1,
          "description": "Counter Designation (appellee)"
        }
      ],
      "date_created": "2019-05-30T00:27:36.388736Z",
      "date_modified": "2019-05-30T00:27:36.389780Z",
      "date_filed": "2019-05-29",
      "entry_number": 43,
      "recap_sequence_number": "2019-05-29.001",
      "pacer_sequence_number": 129,
      "description": ""
    }
  ],
  "parties": [],
  "original_court_info": null,
  "bankruptcy_information": null,
  "claims": [],
  "idb_data": null,
  "absolute_url": "/docket/14882500/fairfield-sentry-limited-in-liquidation-acting-v-chelsea-trust-company/",
  "source": 1,
  "appeal_from_str": "",
  "assigned_to_str": "",
  "referred_to_str": "",
  "panel_str": "",
  "date_created": "2019-04-05T13:15:55.050000Z",
  "date_modified": "2019-05-30T00:27:36.383031Z",
  "date_last_index": null,
  "date_cert_granted": null,
  "date_cert_denied": null,
  "date_argued": null,
  "date_reargued": null,
  "date_reargument_denied": null,
  "date_filed": null,
  "date_terminated": null,
  "date_last_filing": null,
  "case_name_short": "",
  "case_name": "Fairfield Sentry Limited (In Liquidation), acting v. Chelsea Trust Company Limited",
  "case_name_full": "",
  "slug": "fairfield-sentry-limited-in-liquidation-acting-v-chelsea-trust-company",
  "docket_number": "12-01138",
  "docket_number_core": "",
  "pacer_case_id": "225714",
  "cause": "",
  "nature_of_suit": "",
  "jury_demand": "",
  "jurisdiction_type": "",
  "appellate_fee_status": "",
  "appellate_case_type_information": "",
  "mdl_status": "",
  "filepath_local": null,
  "filepath_ia": "",
  "filepath_ia_json": "",
  "date_blocked": "2019-04-05",
  "blocked": true,
  "court": "nysb",
  "appeal_from": null,
  "assigned_to": null,
  "referred_to": null,
  "panel": []
}