{
  "id": 15263980,
  "docket_entries": [
    {
      "id": 72212085,
      "recap_documents": [
        {
          "id": 76352837,
          "absolute_url": "/docket/15263980/1/william-h-miller/",
          "date_created": "2019-05-12T08:20:00.991302Z",
          "date_modified": "2019-05-19T22:21:39.448084Z",
          "sha1": "987647022c7e48458e40d6b4bc692bceece26b0c",
          "page_count": 33,
          "file_size": 295895,
          "filepath_local": "recap/gov.uscourts.ilnb.1053579/gov.uscourts.ilnb.1053579.1.0.pdf",
          "filepath_ia": "https://archive.org/download/gov.uscourts.ilnb.1053579/gov.uscourts.ilnb.1053579.1.0.pdf",
          "ia_upload_failure_count": null,
          "thumbnail": null,
          "thumbnail_status": 0,
          "ocr_status": 2,
          "date_upload": null,
          "document_number": "1",
          "attachment_number": null,
          "pacer_doc_id": "066029521467",
          "is_available": true,
          "is_free_on_pacer": null,
          "is_sealed": null,
          "document_type": 1,
          "description": ""
        }
      ],
      "date_created": "2019-05-12T08:20:00.944112Z",
      "date_modified": "2019-05-12T08:20:00.957534Z",
      "date_filed": "2010-10-24",
      "entry_number": 1,
      "recap_sequence_number": "2010-10-24.001",
      "pacer_sequence_number": null,
      "description": "Chapter 7 Voluntary Petition Fee Amount $299, Filed by Joseph Dowd on behalf of William H Miller, June M Miller (Dowd, Joseph) Modified on 10/25/2010 to add alias Best Aviation Sales, Inc (Rafacz, Lisa). (Entered: 10/24/2010)"
    },
    {
      "id": 72212093,
      "recap_documents": [
        {
          "id": 76352844,
          "absolute_url": "/docket/15263980/2/william-h-miller/",
          "date_created": "2019-05-12T08:20:01.053772Z",
          "date_modified": "2019-05-12T08:20:01.061569Z",
          "sha1": "",
          "page_count": null,
          "file_size": null,
          "filepath_local": null,
          "filepath_ia": "",
          "ia_upload_failure_count": null,
          "thumbnail": null,
          "thumbnail_status": 0,
          "ocr_status": null,
          "date_upload": null,
          "document_number": "2",
          "attachment_number": null,
          "pacer_doc_id": "",
          "is_available": false,
          "is_free_on_pacer": null,
          "is_sealed": null,
          "document_type": 1,
          "description": ""
        }
      ],
      "date_created": "2019-05-12T08:20:01.026631Z",
      "date_modified": "2019-05-12T08:20:01.031523Z",
      "date_filed": "2010-10-24",
      "entry_number": 2,
      "recap_sequence_number": "2010-10-24.002",
      "pacer_sequence_number": null,
      "description": "Meeting of Creditors with 341(a) meeting to be held on 12/15/2010 at 01:00 PM at DuPage Courthouse, 505 N Cty Farm Road, Rm 2017, Wheaton, Illinois 60187. Objections for Discharge due by 02/14/2011. (Dowd, Joseph) (Entered: 10/24/2010)"
    },
    {
      "id": 72212100,
      "recap_documents": [
        {
          "id": 76352851,
          "absolute_url": "/docket/15263980/3/william-h-miller/",
          "date_created": "2019-05-12T08:20:01.113595Z",
          "date_modified": "2019-05-12T08:20:01.128025Z",
          "sha1": "",
          "page_count": null,
          "file_size": null,
          "filepath_local": null,
          "filepath_ia": "",
          "ia_upload_failure_count": null,
          "thumbnail": null,
          "thumbnail_status": 0,
          "ocr_status": null,
          "date_upload": null,
          "document_number": "3",
          "attachment_number": null,
          "pacer_doc_id": "066029521472",
          "is_available": false,
          "is_free_on_pacer": null,
          "is_sealed": null,
          "document_type": 1,
          "description": ""
        }
      ],
      "date_created": "2019-05-12T08:20:01.080446Z",
      "date_modified": "2019-05-12T08:20:01.085302Z",
      "date_filed": "2010-10-24",
      "entry_number": 3,
      "recap_sequence_number": "2010-10-24.003",
      "pacer_sequence_number": null,
      "description": "Certificate of Credit Counseling Filed by Joseph Dowd on behalf of William H Miller. (Dowd, Joseph) (Entered: 10/24/2010)"
    },
    {
      "id": 72212107,
      "recap_documents": [
        {
          "id": 76352858,
          "absolute_url": "/docket/15263980/4/william-h-miller/",
          "date_created": "2019-05-12T08:20:01.193315Z",
          "date_modified": "2019-05-12T08:20:01.207147Z",
          "sha1": "",
          "page_count": null,
          "file_size": null,
          "filepath_local": null,
          "filepath_ia": "",
          "ia_upload_failure_count": null,
          "thumbnail": null,
          "thumbnail_status": 0,
          "ocr_status": null,
          "date_upload": null,
          "document_number": "4",
          "attachment_number": null,
          "pacer_doc_id": "066029521475",
          "is_available": false,
          "is_free_on_pacer": null,
          "is_sealed": null,
          "document_type": 1,
          "description": ""
        }
      ],
      "date_created": "2019-05-12T08:20:01.152355Z",
      "date_modified": "2019-05-12T08:20:01.163536Z",
      "date_filed": "2010-10-24",
      "entry_number": 4,
      "recap_sequence_number": "2010-10-24.004",
      "pacer_sequence_number": null,
      "description": "Certificate of Credit Counseling Filed by Joseph Dowd on behalf of June M Miller. (Dowd, Joseph) (Entered: 10/24/2010)"
    },
    {
      "id": 72212115,
      "recap_documents": [
        {
          "id": 76352867,
          "absolute_url": "/docket/15263980/5/william-h-miller/",
          "date_created": "2019-05-12T08:20:01.278250Z",
          "date_modified": "2019-05-12T08:20:01.290343Z",
          "sha1": "",
          "page_count": null,
          "file_size": null,
          "filepath_local": null,
          "filepath_ia": "",
          "ia_upload_failure_count": null,
          "thumbnail": null,
          "thumbnail_status": 0,
          "ocr_status": null,
          "date_upload": null,
          "document_number": "5",
          "attachment_number": null,
          "pacer_doc_id": "066029521478",
          "is_available": false,
          "is_free_on_pacer": null,
          "is_sealed": null,
          "document_type": 1,
          "description": ""
        }
      ],
      "date_created": "2019-05-12T08:20:01.233461Z",
      "date_modified": "2019-05-12T08:20:01.246027Z",
      "date_filed": "2010-10-24",
      "entry_number": 5,
      "recap_sequence_number": "2010-10-24.005",
      "pacer_sequence_number": null,
      "description": "Chapter 7 Statement of Current Monthly Income and Means Test Calculation - Form 22A. Filed by Joseph Dowd on behalf of June M Miller, William H Miller. (Dowd, Joseph) (Entered: 10/24/2010)"
    },
    {
      "id": 72212123,
      "recap_documents": [
        {
          "id": 76352874,
          "absolute_url": "/docket/15263980/6/william-h-miller/",
          "date_created": "2019-05-12T08:20:01.339116Z",
          "date_modified": "2019-05-12T08:20:01.347689Z",
          "sha1": "",
          "page_count": null,
          "file_size": null,
          "filepath_local": null,
          "filepath_ia": "",
          "ia_upload_failure_count": null,
          "thumbnail": null,
          "thumbnail_status": 0,
          "ocr_status": null,
          "date_upload": null,
          "document_number": "6",
          "attachment_number": null,
          "pacer_doc_id": "066029521481",
          "is_available": false,
          "is_free_on_pacer": null,
          "is_sealed": null,
          "document_type": 1,
          "description": ""
        }
      ],
      "date_created": "2019-05-12T08:20:01.311523Z",
      "date_modified": "2019-05-12T08:20:01.317724Z",
      "date_filed": "2010-10-24",
      "entry_number": 6,
      "recap_sequence_number": "2010-10-24.006",
      "pacer_sequence_number": null,
      "description": "Declaration Re: Electronic Filing Filed by Joseph Dowd on behalf of June M Miller, William H Miller. (Dowd, Joseph) (Entered: 10/24/2010)"
    },
    {
      "id": 72212127,
      "recap_documents": [
        {
          "id": 76352878,
          "absolute_url": "/docket/15263980/7/william-h-miller/",
          "date_created": "2019-05-12T08:20:01.390709Z",
          "date_modified": "2019-05-12T08:20:01.402935Z",
          "sha1": "",
          "page_count": null,
          "file_size": null,
          "filepath_local": null,
          "filepath_ia": "",
          "ia_upload_failure_count": null,
          "thumbnail": null,
          "thumbnail_status": 0,
          "ocr_status": null,
          "date_upload": null,
          "document_number": "7",
          "attachment_number": null,
          "pacer_doc_id": "066029521484",
          "is_available": false,
          "is_free_on_pacer": null,
          "is_sealed": null,
          "document_type": 1,
          "description": ""
        }
      ],
      "date_created": "2019-05-12T08:20:01.364129Z",
      "date_modified": "2019-05-12T08:20:01.368241Z",
      "date_filed": "2010-10-24",
      "entry_number": 7,
      "recap_sequence_number": "2010-10-24.007",
      "pacer_sequence_number": null,
      "description": "Statement of Social Security Number(s) Filed by Joseph Dowd on behalf of June M Miller, William H Miller. (Dowd, Joseph) (Entered: 10/24/2010)"
    },
    {
      "id": 72212132,
      "recap_documents": [
        {
          "id": 76352884,
          "absolute_url": "/docket/15263980/8/william-h-miller/",
          "date_created": "2019-05-12T08:20:01.466386Z",
          "date_modified": "2019-05-12T08:20:01.481016Z",
          "sha1": "",
          "page_count": null,
          "file_size": null,
          "filepath_local": null,
          "filepath_ia": "",
          "ia_upload_failure_count": null,
          "thumbnail": null,
          "thumbnail_status": 0,
          "ocr_status": null,
          "date_upload": null,
          "document_number": "8",
          "attachment_number": null,
          "pacer_doc_id": "",
          "is_available": false,
          "is_free_on_pacer": null,
          "is_sealed": null,
          "document_type": 1,
          "description": ""
        }
      ],
      "date_created": "2019-05-12T08:20:01.428412Z",
      "date_modified": "2019-05-12T08:20:01.435991Z",
      "date_filed": "2010-10-24",
      "entry_number": 8,
      "recap_sequence_number": "2010-10-24.008",
      "pacer_sequence_number": null,
      "description": "Receipt of Voluntary Petition (Chapter 7)(10-47484) [misc,volp7a] ( 299.00) Filing Fee. Receipt number 15459266. Fee Amount $ 299.00 (U.S. Treasury) (Entered: 10/24/2010)"
    },
    {
      "id": 72212138,
      "recap_documents": [
        {
          "id": 76352886,
          "absolute_url": "/docket/15263980/9/william-h-miller/",
          "date_created": "2019-05-12T08:20:01.535814Z",
          "date_modified": "2019-05-12T08:20:01.549547Z",
          "sha1": "",
          "page_count": null,
          "file_size": null,
          "filepath_local": null,
          "filepath_ia": "",
          "ia_upload_failure_count": null,
          "thumbnail": null,
          "thumbnail_status": 0,
          "ocr_status": null,
          "date_upload": null,
          "document_number": "9",
          "attachment_number": null,
          "pacer_doc_id": "",
          "is_available": false,
          "is_free_on_pacer": null,
          "is_sealed": null,
          "document_type": 1,
          "description": ""
        }
      ],
      "date_created": "2019-05-12T08:20:01.501453Z",
      "date_modified": "2019-05-12T08:20:01.511318Z",
      "date_filed": "2010-10-25",
      "entry_number": 9,
      "recap_sequence_number": "2010-10-25.001",
      "pacer_sequence_number": null,
      "description": "CORRECTIVE ENTRY: to add alias Best Aviation Sales, Inc (RE: 1 Voluntary Petition (Chapter 7)). (Rafacz, Lisa) (Entered: 10/25/2010)"
    },
    {
      "id": 72212139,
      "recap_documents": [
        {
          "id": 76352890,
          "absolute_url": "/docket/15263980/10/william-h-miller/",
          "date_created": "2019-05-12T08:20:01.605909Z",
          "date_modified": "2019-05-12T08:20:01.615437Z",
          "sha1": "",
          "page_count": null,
          "file_size": null,
          "filepath_local": null,
          "filepath_ia": "",
          "ia_upload_failure_count": null,
          "thumbnail": null,
          "thumbnail_status": 0,
          "ocr_status": null,
          "date_upload": null,
          "document_number": "10",
          "attachment_number": null,
          "pacer_doc_id": "066029535968",
          "is_available": false,
          "is_free_on_pacer": null,
          "is_sealed": null,
          "document_type": 1,
          "description": ""
        }
      ],
      "date_created": "2019-05-12T08:20:01.569597Z",
      "date_modified": "2019-05-12T08:20:01.578431Z",
      "date_filed": "2010-10-25",
      "entry_number": 10,
      "recap_sequence_number": "2010-10-25.002",
      "pacer_sequence_number": null,
      "description": "Request for Chapter 7 341 Meeting of Creditors . (Rafacz, Lisa) (Entered: 10/25/2010)"
    },
    {
      "id": 72212143,
      "recap_documents": [
        {
          "id": 76352894,
          "absolute_url": "/docket/15263980/11/william-h-miller/",
          "date_created": "2019-05-12T08:20:01.673609Z",
          "date_modified": "2019-05-12T08:20:01.686484Z",
          "sha1": "",
          "page_count": null,
          "file_size": null,
          "filepath_local": null,
          "filepath_ia": "",
          "ia_upload_failure_count": null,
          "thumbnail": null,
          "thumbnail_status": 0,
          "ocr_status": null,
          "date_upload": null,
          "document_number": "11",
          "attachment_number": null,
          "pacer_doc_id": "066029582116",
          "is_available": false,
          "is_free_on_pacer": null,
          "is_sealed": null,
          "document_type": 1,
          "description": ""
        }
      ],
      "date_created": "2019-05-12T08:20:01.639924Z",
      "date_modified": "2019-05-12T08:20:01.648792Z",
      "date_filed": "2010-10-27",
      "entry_number": 11,
      "recap_sequence_number": "2010-10-27.001",
      "pacer_sequence_number": null,
      "description": "BNC Certificate of Service - Meeting of Creditors. (RE: 10 Request for Chapter 7 341 Meeting of Creditors). No. of Notices: 14. Service Date 10/27/2010. (Admin.) (Entered: 10/27/2010)"
    },
    {
      "id": 72212147,
      "recap_documents": [
        {
          "id": 76352898,
          "absolute_url": "/docket/15263980/12/william-h-miller/",
          "date_created": "2019-05-12T08:20:01.751435Z",
          "date_modified": "2019-05-12T08:20:01.764408Z",
          "sha1": "",
          "page_count": null,
          "file_size": null,
          "filepath_local": null,
          "filepath_ia": "",
          "ia_upload_failure_count": null,
          "thumbnail": null,
          "thumbnail_status": 0,
          "ocr_status": null,
          "date_upload": null,
          "document_number": "12",
          "attachment_number": null,
          "pacer_doc_id": "066029868148",
          "is_available": false,
          "is_free_on_pacer": null,
          "is_sealed": null,
          "document_type": 1,
          "description": ""
        }
      ],
      "date_created": "2019-05-12T08:20:01.710323Z",
      "date_modified": "2019-05-12T08:20:01.720828Z",
      "date_filed": "2010-11-16",
      "entry_number": 12,
      "recap_sequence_number": "2010-11-16.001",
      "pacer_sequence_number": null,
      "description": "Notice of Required Document(s) for Discharge for Both Debtors (Riddick, Debbie) (Entered: 11/16/2010)"
    },
    {
      "id": 72212151,
      "recap_documents": [
        {
          "id": 76352902,
          "absolute_url": "/docket/15263980/13/william-h-miller/",
          "date_created": "2019-05-12T08:20:01.817095Z",
          "date_modified": "2019-05-12T08:20:01.827875Z",
          "sha1": "",
          "page_count": null,
          "file_size": null,
          "filepath_local": null,
          "filepath_ia": "",
          "ia_upload_failure_count": null,
          "thumbnail": null,
          "thumbnail_status": 0,
          "ocr_status": null,
          "date_upload": null,
          "document_number": "13",
          "attachment_number": null,
          "pacer_doc_id": "066029928837",
          "is_available": false,
          "is_free_on_pacer": null,
          "is_sealed": null,
          "document_type": 1,
          "description": ""
        }
      ],
      "date_created": "2019-05-12T08:20:01.790072Z",
      "date_modified": "2019-05-12T08:20:01.794519Z",
      "date_filed": "2010-11-18",
      "entry_number": 13,
      "recap_sequence_number": "2010-11-18.001",
      "pacer_sequence_number": null,
      "description": "BNC Certificate of Service - Notice of Required Document(s) for Discharge (RE: 12 Notice of Required Document(s) for Discharge). No. of Notices: 2. Service Date 11/18/2010. (Admin.) (Entered: 11/18/2010)"
    },
    {
      "id": 72212156,
      "recap_documents": [
        {
          "id": 76352907,
          "absolute_url": "/docket/15263980/14/william-h-miller/",
          "date_created": "2019-05-12T08:20:01.888291Z",
          "date_modified": "2019-05-12T08:20:01.898125Z",
          "sha1": "",
          "page_count": null,
          "file_size": null,
          "filepath_local": null,
          "filepath_ia": "",
          "ia_upload_failure_count": null,
          "thumbnail": null,
          "thumbnail_status": 0,
          "ocr_status": null,
          "date_upload": null,
          "document_number": "14",
          "attachment_number": null,
          "pacer_doc_id": "",
          "is_available": false,
          "is_free_on_pacer": null,
          "is_sealed": null,
          "document_type": 1,
          "description": ""
        }
      ],
      "date_created": "2019-05-12T08:20:01.856129Z",
      "date_modified": "2019-05-12T08:20:01.864301Z",
      "date_filed": "2010-11-19",
      "entry_number": 14,
      "recap_sequence_number": "2010-11-19.001",
      "pacer_sequence_number": null,
      "description": "Request for Service of Notices. American Express Bank FSB, POB 3001 Malvern PA 19355-0701 (Weisman, Gilbert) (Entered: 11/19/2010)"
    },
    {
      "id": 72212160,
      "recap_documents": [
        {
          "id": 76352911,
          "absolute_url": "/docket/15263980/15/william-h-miller/",
          "date_created": "2019-05-12T08:20:01.948099Z",
          "date_modified": "2019-05-12T08:20:01.959057Z",
          "sha1": "",
          "page_count": null,
          "file_size": null,
          "filepath_local": null,
          "filepath_ia": "",
          "ia_upload_failure_count": null,
          "thumbnail": null,
          "thumbnail_status": 0,
          "ocr_status": null,
          "date_upload": null,
          "document_number": "15",
          "attachment_number": null,
          "pacer_doc_id": "",
          "is_available": false,
          "is_free_on_pacer": null,
          "is_sealed": null,
          "document_type": 1,
          "description": ""
        }
      ],
      "date_created": "2019-05-12T08:20:01.919395Z",
      "date_modified": "2019-05-12T08:20:01.924643Z",
      "date_filed": "2010-12-16",
      "entry_number": 15,
      "recap_sequence_number": "2010-12-16.001",
      "pacer_sequence_number": null,
      "description": "Chapter 7 Trustee's Report of No Distribution: I, Brenda Porter Helms, having been appointed trustee of the estate of the above-named debtor(s), report that I have neither received any property nor paid any money on account of this estate; that I have made a diligent inquiry into the financial affairs of the debtor(s) and the location of the property belonging to the estate; and that there is no property available for distribution from the estate over and above that exempted by law. Pursuant to Fed R Bank P 5009, I hereby certify that the estate of the above-named debtor(s) has been fully administered. I request that I be discharged from any further duties as trustee. Key information about this case as reported in schedules filed by the debtor(s) or otherwise found in the case record: This case was pending for 2 months. Assets Abandoned (without deducting any secured claims): $ 252000.00, Assets Exempt: $ 248871.00, Claims Scheduled: $ 732588.33, Claims Asserted: Not Applicable, Claims scheduled to be discharged without payment (without deducting the value of collateral or debts excepted from discharge): $ 732588.33. Filed by Trustee Brenda Porter Helms ESQ (RE: 2 Meeting (Chapter 7)). (Helms, Brenda) (Entered: 12/16/2010)"
    },
    {
      "id": 72212164,
      "recap_documents": [
        {
          "id": 76352915,
          "absolute_url": "/docket/15263980/16/william-h-miller/",
          "date_created": "2019-05-12T08:20:02.013245Z",
          "date_modified": "2019-05-12T08:20:02.025445Z",
          "sha1": "",
          "page_count": null,
          "file_size": null,
          "filepath_local": null,
          "filepath_ia": "",
          "ia_upload_failure_count": null,
          "thumbnail": null,
          "thumbnail_status": 0,
          "ocr_status": null,
          "date_upload": null,
          "document_number": "16",
          "attachment_number": null,
          "pacer_doc_id": "066030788459",
          "is_available": false,
          "is_free_on_pacer": null,
          "is_sealed": null,
          "document_type": 1,
          "description": ""
        }
      ],
      "date_created": "2019-05-12T08:20:01.982046Z",
      "date_modified": "2019-05-12T08:20:01.987341Z",
      "date_filed": "2011-01-22",
      "entry_number": 16,
      "recap_sequence_number": "2011-01-22.001",
      "pacer_sequence_number": null,
      "description": "Debtor's Certification of Completion of Instructional Course Concerning Personal Financial Management Filed by Joseph Dowd on behalf of June M Miller. (Dowd, Joseph) (Entered: 01/22/2011)"
    },
    {
      "id": 72212168,
      "recap_documents": [
        {
          "id": 76352919,
          "absolute_url": "/docket/15263980/17/william-h-miller/",
          "date_created": "2019-05-12T08:20:02.066127Z",
          "date_modified": "2019-05-12T08:20:02.075791Z",
          "sha1": "",
          "page_count": null,
          "file_size": null,
          "filepath_local": null,
          "filepath_ia": "",
          "ia_upload_failure_count": null,
          "thumbnail": null,
          "thumbnail_status": 0,
          "ocr_status": null,
          "date_upload": null,
          "document_number": "17",
          "attachment_number": null,
          "pacer_doc_id": "066030788462",
          "is_available": false,
          "is_free_on_pacer": null,
          "is_sealed": null,
          "document_type": 1,
          "description": ""
        }
      ],
      "date_created": "2019-05-12T08:20:02.043129Z",
      "date_modified": "2019-05-12T08:20:02.047500Z",
      "date_filed": "2011-01-22",
      "entry_number": 17,
      "recap_sequence_number": "2011-01-22.002",
      "pacer_sequence_number": null,
      "description": "Debtor's Certification of Completion of Instructional Course Concerning Personal Financial Management Filed by Joseph Dowd on behalf of William H Miller. (Dowd, Joseph) (Entered: 01/22/2011)"
    },
    {
      "id": 72212172,
      "recap_documents": [
        {
          "id": 76352923,
          "absolute_url": "/docket/15263980/18/william-h-miller/",
          "date_created": "2019-05-12T08:20:02.134824Z",
          "date_modified": "2019-05-12T08:20:02.143303Z",
          "sha1": "",
          "page_count": null,
          "file_size": null,
          "filepath_local": null,
          "filepath_ia": "",
          "ia_upload_failure_count": null,
          "thumbnail": null,
          "thumbnail_status": 0,
          "ocr_status": null,
          "date_upload": null,
          "document_number": "18",
          "attachment_number": null,
          "pacer_doc_id": "066031101966",
          "is_available": false,
          "is_free_on_pacer": null,
          "is_sealed": null,
          "document_type": 1,
          "description": ""
        }
      ],
      "date_created": "2019-05-12T08:20:02.107131Z",
      "date_modified": "2019-05-12T08:20:02.112878Z",
      "date_filed": "2011-02-15",
      "entry_number": 18,
      "recap_sequence_number": "2011-02-15.001",
      "pacer_sequence_number": null,
      "description": "Request for Discharge Order for Both Debtors . (Marola, Rosalie) (Entered: 02/15/2011)"
    },
    {
      "id": 72212176,
      "recap_documents": [
        {
          "id": 76352927,
          "absolute_url": "/docket/15263980/19/william-h-miller/",
          "date_created": "2019-05-12T08:20:02.186843Z",
          "date_modified": "2019-05-12T08:20:02.196839Z",
          "sha1": "",
          "page_count": null,
          "file_size": null,
          "filepath_local": null,
          "filepath_ia": "",
          "ia_upload_failure_count": null,
          "thumbnail": null,
          "thumbnail_status": 0,
          "ocr_status": null,
          "date_upload": null,
          "document_number": "19",
          "attachment_number": null,
          "pacer_doc_id": "066031154438",
          "is_available": false,
          "is_free_on_pacer": null,
          "is_sealed": null,
          "document_type": 1,
          "description": ""
        }
      ],
      "date_created": "2019-05-12T08:20:02.159139Z",
      "date_modified": "2019-05-12T08:20:02.166380Z",
      "date_filed": "2011-02-17",
      "entry_number": 19,
      "recap_sequence_number": "2011-02-17.001",
      "pacer_sequence_number": null,
      "description": "BNC Certificate of Service - Order of Discharge. (RE: 18 Request for Discharge Order). No. of Notices: 14. Service Date 02/17/2011. (Admin.) (Entered: 02/17/2011)"
    },
    {
      "id": 72212180,
      "recap_documents": [
        {
          "id": 76352931,
          "absolute_url": "/docket/15263980/20/william-h-miller/",
          "date_created": "2019-05-12T08:20:02.252587Z",
          "date_modified": "2019-05-12T08:20:02.263455Z",
          "sha1": "",
          "page_count": null,
          "file_size": null,
          "filepath_local": null,
          "filepath_ia": "",
          "ia_upload_failure_count": null,
          "thumbnail": null,
          "thumbnail_status": 0,
          "ocr_status": null,
          "date_upload": null,
          "document_number": "20",
          "attachment_number": null,
          "pacer_doc_id": "",
          "is_available": false,
          "is_free_on_pacer": null,
          "is_sealed": null,
          "document_type": 1,
          "description": ""
        }
      ],
      "date_created": "2019-05-12T08:20:02.229044Z",
      "date_modified": "2019-05-12T08:20:02.234356Z",
      "date_filed": "2011-02-18",
      "entry_number": 20,
      "recap_sequence_number": "2011-02-18.001",
      "pacer_sequence_number": null,
      "description": "Bankruptcy Case Closed and Trustee Discharged . (Marola, Rosalie) (Entered: 02/18/2011)"
    }
  ],
  "parties": [
    {
      "id": 6157931,
      "attorneys": [
        {
          "id": 4234146,
          "roles": [
            {
              "id": 77379691,
              "role": 10,
              "role_raw": "",
              "date_action": null
            },
            {
              "id": 77379692,
              "role": 10,
              "role_raw": "",
              "date_action": null
            }
          ],
          "date_created": "2019-05-12T08:20:02.310926Z",
          "date_modified": "2019-05-12T08:20:02.351493Z",
          "name": "Joseph Dowd",
          "contact_raw": "Joseph P. Dowd, Lawyer\nP O Box 376\nDes Plaines, IL 60016\n847 827-7806\nEmail:\n",
          "phone": "(847) 827-7806",
          "fax": "",
          "email": ""
        }
      ],
      "party_types": [
        {
          "id": 7128108,
          "criminal_counts": [],
          "criminal_complaints": [],
          "name": "Debtor",
          "date_terminated": null,
          "extra_info": "714 Parkside\nElmhurst, IL 60126\nDU PAGE-IL\nSSN / ITIN: xxx-xx-2445\nTax ID / EIN: 36-3603240",
          "highest_offense_level_opening": "",
          "highest_offense_level_terminated": ""
        }
      ],
      "date_created": "2019-05-12T08:20:02.293210Z",
      "date_modified": "2019-05-12T08:20:02.293254Z",
      "name": "William H Miller",
      "extra_info": ""
    },
    {
      "id": 6157932,
      "attorneys": [
        {
          "id": 4234146,
          "roles": [
            {
              "id": 77379691,
              "role": 10,
              "role_raw": "",
              "date_action": null
            },
            {
              "id": 77379692,
              "role": 10,
              "role_raw": "",
              "date_action": null
            }
          ],
          "date_created": "2019-05-12T08:20:02.310926Z",
          "date_modified": "2019-05-12T08:20:02.351493Z",
          "name": "Joseph Dowd",
          "contact_raw": "Joseph P. Dowd, Lawyer\nP O Box 376\nDes Plaines, IL 60016\n847 827-7806\nEmail:\n",
          "phone": "(847) 827-7806",
          "fax": "",
          "email": ""
        }
      ],
      "party_types": [
        {
          "id": 7128109,
          "criminal_counts": [],
          "criminal_complaints": [],
          "name": "Debtor",
          "date_terminated": null,
          "extra_info": "714 Parkside\nElmhurst, IL 60126\nDU PAGE-IL\nSSN / ITIN: xxx-xx-4617\nTax ID / EIN: 36-3603240",
          "highest_offense_level_opening": "",
          "highest_offense_level_terminated": ""
        }
      ],
      "date_created": "2019-05-12T08:20:02.332869Z",
      "date_modified": "2019-05-12T08:20:02.332906Z",
      "name": "June M Miller",
      "extra_info": ""
    },
    {
      "id": 6157933,
      "attorneys": [],
      "party_types": [
        {
          "id": 7128110,
          "criminal_counts": [],
          "criminal_complaints": [],
          "name": "Trustee",
          "date_terminated": null,
          "extra_info": "The Helms Law Firm, P.C.\n3400 West Lawrence\nChicago, IL 60625\n773-463-6427",
          "highest_offense_level_opening": "",
          "highest_offense_level_terminated": ""
        }
      ],
      "date_created": "2019-05-12T08:20:02.361681Z",
      "date_modified": "2019-05-12T08:20:02.361724Z",
      "name": "Brenda Porter Helms, ESQ",
      "extra_info": ""
    },
    {
      "id": 6157934,
      "attorneys": [],
      "party_types": [
        {
          "id": 7128111,
          "criminal_counts": [],
          "criminal_complaints": [],
          "name": "U.S. Trustee",
          "date_terminated": null,
          "extra_info": "Office of the U.S. Trustee, Region 11\n219 S Dearborn St\nRoom 873\nChicago, IL 60604\n312-886-5785",
          "highest_offense_level_opening": "",
          "highest_offense_level_terminated": ""
        }
      ],
      "date_created": "2019-05-12T08:20:02.368879Z",
      "date_modified": "2019-05-12T08:20:02.368932Z",
      "name": "Patrick S Layng",
      "extra_info": ""
    }
  ],
  "original_court_info": null,
  "bankruptcy_information": null,
  "claims": [],
  "idb_data": null,
  "absolute_url": "/docket/15263980/william-h-miller/",
  "source": 1,
  "appeal_from_str": "",
  "assigned_to_str": "John H. Squires",
  "referred_to_str": "",
  "panel_str": "",
  "date_created": "2019-05-12T08:20:00.484364Z",
  "date_modified": "2019-05-12T08:21:48.636922Z",
  "date_last_index": "2019-05-12T08:21:48.636504Z",
  "date_cert_granted": null,
  "date_cert_denied": null,
  "date_argued": null,
  "date_reargued": null,
  "date_reargument_denied": null,
  "date_filed": "2010-10-24",
  "date_terminated": "2011-02-18",
  "date_last_filing": null,
  "case_name_short": "William H Miller",
  "case_name": "William H Miller",
  "case_name_full": "",
  "slug": "william-h-miller",
  "docket_number": "10-47484",
  "docket_number_core": "",
  "pacer_case_id": "1053579",
  "cause": "",
  "nature_of_suit": "",
  "jury_demand": "",
  "jurisdiction_type": "",
  "appellate_fee_status": "",
  "appellate_case_type_information": "",
  "mdl_status": "",
  "filepath_local": null,
  "filepath_ia": "",
  "filepath_ia_json": "",
  "date_blocked": "2019-05-12",
  "blocked": true,
  "court": "ilnb",
  "appeal_from": null,
  "assigned_to": null,
  "referred_to": null,
  "panel": []
}