{
  "id": 15988743,
  "docket_entries": [
    {
      "id": 96775442,
      "recap_documents": [
        {
          "id": 100995130,
          "absolute_url": "/docket/15988743/9/juniper-bond-holdings-i-llc/",
          "date_created": "2019-07-30T20:22:04.547956Z",
          "date_modified": "2019-07-30T20:22:04.550307Z",
          "sha1": "",
          "page_count": null,
          "file_size": null,
          "filepath_local": null,
          "filepath_ia": "",
          "ia_upload_failure_count": null,
          "thumbnail": null,
          "thumbnail_status": 0,
          "ocr_status": null,
          "date_upload": null,
          "document_number": "9",
          "attachment_number": null,
          "pacer_doc_id": "126020094903",
          "is_available": false,
          "is_free_on_pacer": null,
          "is_sealed": null,
          "document_type": 1,
          "description": "Application, Final Decree"
        }
      ],
      "date_created": "2019-07-30T20:22:04.542862Z",
      "date_modified": "2019-07-30T20:22:04.543666Z",
      "date_filed": "2019-07-30",
      "entry_number": 9,
      "recap_sequence_number": "2019-07-30.001",
      "pacer_sequence_number": 53,
      "description": ""
    },
    {
      "id": 97909389,
      "recap_documents": [
        {
          "id": 102138364,
          "absolute_url": "/docket/15988743/10/juniper-bond-holdings-i-llc/",
          "date_created": "2019-08-08T17:13:27.111809Z",
          "date_modified": "2019-08-08T17:13:27.115411Z",
          "sha1": "",
          "page_count": null,
          "file_size": null,
          "filepath_local": null,
          "filepath_ia": "",
          "ia_upload_failure_count": null,
          "thumbnail": null,
          "thumbnail_status": 0,
          "ocr_status": null,
          "date_upload": null,
          "document_number": "10",
          "attachment_number": null,
          "pacer_doc_id": "126020119912",
          "is_available": false,
          "is_free_on_pacer": null,
          "is_sealed": null,
          "document_type": 1,
          "description": "Application, Final Decree"
        }
      ],
      "date_created": "2019-08-08T17:13:27.105895Z",
      "date_modified": "2019-08-08T17:13:27.106669Z",
      "date_filed": "2019-08-08",
      "entry_number": 10,
      "recap_sequence_number": "2019-08-08.001",
      "pacer_sequence_number": 55,
      "description": ""
    }
  ],
  "parties": [],
  "original_court_info": null,
  "bankruptcy_information": null,
  "claims": [],
  "idb_data": null,
  "absolute_url": "/docket/15988743/juniper-bond-holdings-i-llc/",
  "source": 1,
  "appeal_from_str": "",
  "assigned_to_str": "",
  "referred_to_str": "",
  "panel_str": "",
  "date_created": "2019-07-30T20:22:04.537932Z",
  "date_modified": "2019-08-08T17:13:27.101948Z",
  "date_last_index": null,
  "date_cert_granted": null,
  "date_cert_denied": null,
  "date_argued": null,
  "date_reargued": null,
  "date_reargument_denied": null,
  "date_filed": null,
  "date_terminated": null,
  "date_last_filing": null,
  "case_name_short": "",
  "case_name": "Juniper Bond Holdings I LLC",
  "case_name_full": "",
  "slug": "juniper-bond-holdings-i-llc",
  "docket_number": "14-22504",
  "docket_number_core": "",
  "pacer_case_id": "248829",
  "cause": "",
  "nature_of_suit": "",
  "jury_demand": "",
  "jurisdiction_type": "",
  "appellate_fee_status": "",
  "appellate_case_type_information": "",
  "mdl_status": "",
  "filepath_local": null,
  "filepath_ia": "",
  "filepath_ia_json": "",
  "date_blocked": "2019-07-30",
  "blocked": true,
  "court": "nysb",
  "appeal_from": null,
  "assigned_to": null,
  "referred_to": null,
  "panel": []
}