{
  "id": 7140883,
  "docket_entries": [
    {
      "id": 28660992,
      "recap_documents": [
        {
          "id": 30749890,
          "absolute_url": "/docket/7140883/14/francisca-sanchez/",
          "date_created": "2018-06-13T01:23:54.422471Z",
          "date_modified": "2018-06-13T01:23:54.425589Z",
          "sha1": "",
          "page_count": null,
          "file_size": null,
          "filepath_local": null,
          "filepath_ia": "",
          "ia_upload_failure_count": null,
          "thumbnail": null,
          "thumbnail_status": 0,
          "ocr_status": null,
          "date_upload": null,
          "document_number": "14",
          "attachment_number": null,
          "pacer_doc_id": "036018025473",
          "is_available": false,
          "is_free_on_pacer": null,
          "is_sealed": null,
          "document_type": 1,
          "description": "Discharge of Debtor(s), Chapter 7 (BNC)"
        }
      ],
      "date_created": "2018-06-13T01:23:54.415939Z",
      "date_modified": "2018-06-13T01:23:54.416923Z",
      "date_filed": "2018-06-13",
      "entry_number": 14,
      "recap_sequence_number": "2018-06-13.001",
      "pacer_sequence_number": null,
      "description": ""
    },
    {
      "id": 29030930,
      "recap_documents": [
        {
          "id": 31121912,
          "absolute_url": "/docket/7140883/15/francisca-sanchez/",
          "date_created": "2018-06-16T04:29:18.667592Z",
          "date_modified": "2018-06-16T04:29:18.669578Z",
          "sha1": "",
          "page_count": null,
          "file_size": null,
          "filepath_local": null,
          "filepath_ia": "",
          "ia_upload_failure_count": null,
          "thumbnail": null,
          "thumbnail_status": 0,
          "ocr_status": null,
          "date_upload": null,
          "document_number": "15",
          "attachment_number": null,
          "pacer_doc_id": "036018033320",
          "is_available": false,
          "is_free_on_pacer": null,
          "is_sealed": null,
          "document_type": 1,
          "description": "BNC Court Certificate of Notice re Discharge of Debtor, Chapter 7"
        }
      ],
      "date_created": "2018-06-16T04:29:18.663313Z",
      "date_modified": "2018-06-16T04:29:18.663930Z",
      "date_filed": "2018-06-16",
      "entry_number": 15,
      "recap_sequence_number": "2018-06-16.001",
      "pacer_sequence_number": null,
      "description": ""
    }
  ],
  "parties": [],
  "original_court_info": null,
  "bankruptcy_information": null,
  "claims": [],
  "idb_data": null,
  "absolute_url": "/docket/7140883/francisca-sanchez/",
  "source": 1,
  "appeal_from_str": "",
  "assigned_to_str": "",
  "referred_to_str": "",
  "panel_str": "",
  "date_created": "2018-06-13T01:23:54.411741Z",
  "date_modified": "2018-10-27T22:19:16.436698Z",
  "date_last_index": null,
  "date_cert_granted": null,
  "date_cert_denied": null,
  "date_argued": null,
  "date_reargued": null,
  "date_reargument_denied": null,
  "date_filed": null,
  "date_terminated": null,
  "date_last_filing": null,
  "case_name_short": "Francisca Sanchez",
  "case_name": "Francisca Sanchez",
  "case_name_full": "",
  "slug": "francisca-sanchez",
  "docket_number": "18-01263",
  "docket_number_core": "",
  "pacer_case_id": "426454",
  "cause": "",
  "nature_of_suit": "",
  "jury_demand": "",
  "jurisdiction_type": "",
  "appellate_fee_status": "",
  "appellate_case_type_information": "",
  "mdl_status": "",
  "filepath_local": null,
  "filepath_ia": "",
  "filepath_ia_json": "https://archive.org/download/gov.uscourts.casb.426454/gov.uscourts.casb.426454.docket.json",
  "date_blocked": "2018-06-12",
  "blocked": true,
  "court": "casb",
  "appeal_from": null,
  "assigned_to": null,
  "referred_to": null,
  "panel": []
}